Workbook

Sheet BhavCopy_NSE_CM
A1: SYMBOL+Series | B1: TradDt | C1: BizDt | D1: Sgmt | E1: Src | F1: FinInstrmTp | G1: FinInstrmId | H1: ISIN | I1: TckrSymb | J1: SctySrs | K1: XpryDt | L1: FininstrmActlXpryDt | M1: StrkPric | N1: OptnTp | O1: FinInstrmNm | P1: OpnPric | Q1: HghPric | R1: LwPric | S1: ClsPric | T1: LastPric | U1: PrvsClsgPric | V1: UndrlygPric | W1: SttlmPric | X1: OpnIntrst | Y1: ChngInOpnIntrst | Z1: TtlTradgVol | AA1: TtlTrfVal | AB1: TtlNbOfTxsExctd | AC1: SsnId | AD1: NewBrdLotQty | AE1: Rmks | AF1: Rsvd1 | AG1: Rsvd2 | AH1: Rsvd3 | AI1: Rsvd4
A2: =CONCATENATE(I2,J2) -> SGBJUN28GB | B2: 46273 | C2: 46273 | D2: CM | E2: NSE | F2: STK | G2: 19078 | H2: IN0020200104 | I2: SGBJUN28 | J2: GB | O2: 2.5%GOLDBONDS2028SR-III | P2: 15116.04 | Q2: 15195.03 | R2: 15070 | S2: 15070 | T2: 15070 | U2: 15085.7 | W2: 15070 | Z2: 149 | AA2: 2251747.5 | AB2: 34 | AC2: F1 | AD2: 1
A3: =CONCATENATE(I3,J3) -> SGBN28VIIIGB | B3: 46273 | C3: 46273 | D3: CM | E3: NSE | F3: STK | G3: 1342 | H3: IN0020200286 | I3: SGBN28VIII | J3: GB | O3: 2.5%GOLDBONDS2028SR-VIII | P3: 15157 | Q3: 15246 | R3: 15052 | S3: 15124.99 | T3: 15124.99 | U3: 15095.19 | W3: 15124.99 | Z3: 60 | AA3: 908678.92 | AB3: 24 | AC3: F1 | AD3: 1
A4: =CONCATENATE(I4,J4) -> SGBMAY29IGB | B4: 46273 | C4: 46273 | D4: CM | E4: NSE | F4: STK | G4: 3742 | H4: IN0020210053 | I4: SGBMAY29I | J4: GB | O4: 2.5%GOLDBONDS2029SR-I | P4: 15017.56 | Q4: 15224.99 | R4: 15016 | S4: 15139.28 | T4: 15180 | U4: 15093.03 | W4: 15138.2 | Z4: 446 | AA4: 6763741.6 | AB4: 60 | AC4: F1 | AD4: 1
A5: =CONCATENATE(I5,J5) -> SGBJUN29IIGB | B5: 46273 | C5: 46273 | D5: CM | E5: NSE | F5: STK | G5: 3743 | H5: IN0020210061 | I5: SGBJUN29II | J5: GB | O5: 2.5%GOLDBONDS2029SR-II | P5: 15025 | Q5: 15188 | R5: 15025 | S5: 15068.84 | T5: 15063 | U5: 15090 | W5: 15074.5 | Z5: 43 | AA5: 650755.89 | AB5: 21 | AC5: F1 | AD5: 1
A6: =CONCATENATE(I6,J6) -> SGBJU29IIIGB | B6: 46273 | C6: 46273 | D6: CM | E6: NSE | F6: STK | G6: 3800 | H6: IN0020210087 | I6: SGBJU29III | J6: GB | O6: 2.5%GOLDBONDS2029SR-III | P6: 15015.01 | Q6: 15349 | R6: 15015.01 | S6: 15067.37 | T6: 15067.37 | U6: 15079.88 | W6: 15067.37 | Z6: 52 | AA6: 786679.41 | AB6: 27 | AC6: F1 | AD6: 1
A7: =CONCATENATE(I7,J7) -> SGBSEP29VIGB | B7: 46273 | C7: 46273 | D7: CM | E7: NSE | F7: STK | G7: 5575 | H7: IN0020210145 | I7: SGBSEP29VI | J7: GB | O7: 2.5%GOLDBONDS2029SR-VI | P7: 15101 | Q7: 15389 | R7: 15012 | S7: 15052.16 | T7: 15060 | U7: 15037.44 | W7: 15046.34 | Z7: 126 | AA7: 1904401.7 | AB7: 45 | AC7: F1 | AD7: 1
A8: =CONCATENATE(I8,J8) -> SGBNV29VIIGB | B8: 46273 | C8: 46273 | D8: CM | E8: NSE | F8: STK | G8: 6518 | H8: IN0020210178 | I8: SGBNV29VII | J8: GB | O8: 2.5%GOLDBONDS2029SR-VII | P8: 15151 | Q8: 15289 | R8: 15100.33 | S8: 15118.29 | T8: 15150 | U8: 15100.33 | W8: 15098 | Z8: 50 | AA8: 757623.33 | AB8: 16 | AC8: F1 | AD8: 1
A9: =CONCATENATE(I9,J9) -> SGBOCT26GB | B9: 46273 | C9: 46273 | D9: CM | E9: NSE | F9: STK | G9: 5960 | H9: IN0020180249 | I9: SGBOCT26 | J9: GB | O9: 2.50%GOLDBONDS2026SR-II | P9: 15150 | Q9: 15150 | R9: 15150 | S9: 15150 | T9: 15150 | U9: 15000 | W9: 15150 | Z9: 1 | AA9: 15150 | AB9: 1 | AC9: F1 | AD9: 1
A10: =CONCATENATE(I10,J10) -> SGBDEC26GB | B10: 46273 | C10: 46273 | D10: CM | E10: NSE | F10: STK | G10: 7654 | H10: IN0020180389 | I10: SGBDEC26 | J10: GB | O10: 2.50%GOLDBONDS2026SR-IV | P10: 15100.01 | Q10: 15100.01 | R10: 15100.01 | S10: 15100.01 | T10: 15100.01 | U10: 15100.9 | W10: 15100.01 | Z10: 1 | AA10: 15100.01 | AB10: 1 | AC10: F1 | AD10: 1
A11: =CONCATENATE(I11,J11) -> SGBJUN27GB | B11: 46273 | C11: 46273 | D11: CM | E11: NSE | F11: STK | G11: 10261 | H11: IN0020190073 | I11: SGBJUN27 | J11: GB | O11: 2.50%GOLDBONDS2027SR-I | P11: 15000 | Q11: 15100 | R11: 15000 | S11: 15056.83 | T11: 15050 | U11: 15045.45 | W11: 15056.83 | Z11: 70 | AA11: 1053079 | AB11: 17 | AC11: F1 | AD11: 1
A12: =CONCATENATE(I12,J12) -> SGBJUL27GB | B12: 46273 | C12: 46273 | D12: CM | E12: NSE | F12: STK | G12: 11154 | H12: IN0020190081 | I12: SGBJUL27 | J12: GB | O12: 2.50%GOLDBONDS2027SR-II | P12: 15025.5 | Q12: 15025.5 | R12: 15001 | S12: 15001 | T12: 15001 | U12: 14911.02 | W12: 15001 | Z12: 2 | AA12: 30026.5 | AB12: 2 | AC12: F1 | AD12: 1
A13: =CONCATENATE(I13,J13) -> SGBAUG27GB | B13: 46273 | C13: 46273 | D13: CM | E13: NSE | F13: STK | G13: 12904 | H13: IN0020190107 | I13: SGBAUG27 | J13: GB | O13: 2.50%GOLDBONDS2027SR-III | P13: 15101 | Q13: 15120 | R13: 15066.54 | S13: 15070.25 | T13: 15066.54 | U13: 15066.54 | W13: 15074.16 | Z13: 69 | AA13: 1041522.5 | AB13: 16 | AC13: F1 | AD13: 1
... A3653: =CONCATENATE(I3653,J3653) -> ZYDUSWELLEQ | B3653: 46273 | C3653: 46273 | D3653: CM | E3653: NSE | F3653: STK | G3653: 17635 | H3653: INE768C01028 | I3653: ZYDUSWELL | J3653: EQ | O3653: ZYDUS WELLNESS LIMITED | P3653: 555.35 | Q3653: 562.95 | R3653: 554.7 | S3653: 558.15 | T3653: 557.8 | U3653: 555.35 | W3653: 558.18 | Z3653: 321731 | AA3653: 1.7970293e+08 | AB3653: 17884 | AC3653: F1 | AD3653: 1

Sheet Range 
B1: High | C1: Low | D1: Difference | E1: Trg 1- 13 | F1: Trg 2 -21 | G1: Trg 3 - 34 | H1: Trg 4 -55 | I1: Trg 5 -89 | J1: Trg-144 | K1: 144% Still Price | L1: % Change from Lows | M1: Curr mkt price | N1: Previous close | O1: 10% correction | P1: 20% correction | Q1: No | S1: Weekly Close | T1: Support - Resistance | U1: Weekly Close Date
A2: 46268 | C2: Check lows support | M2: Today's Close | N2: Previous close | S2: 07.08.2026 | T2: 09.08.2026
A3: Ashapurmin | B3: 924 | C3: 518 | D3: =B3-C3 -> 406 | E3: =D3*13%+C3 -> 570.78 | F3: =D3*21%+C3 -> 603.26 | G3: =D3*34%+C3 -> 656.04 | H3: =D3*55%+C3 -> 741.3 | I3: =D3*89%+C3 -> 879.34 | J3: =E3*144%+D3 -> 1227.9232 | L3: =(M3*100/C3)-100 -> 6.0521236 | M3: =VLOOKUP(A3&"EQ",BhavCopy_NSE_CM!A:U,19,0) -> 549.35 | N3: =VLOOKUP(A3&"EQ",BhavCopy_NSE_CM!A:U,21,0) -> 538.15 | O3: =B3-M3*10% -> 869.065 | P3: =B3-M3*20% -> 814.13 | Q3: 1 | R3: =M3<I3 -> TRUE | S3: 901 | T3: 620-670-760-810-925-990
A4: Astramicro | B4: 1861.6 | C4: 1190 | D4: =B4-C4 -> 671.6 | E4: =D4*13%+C4 -> 1277.308 | F4: =D4*21%+C4 -> 1331.036 | G4: =D4*34%+C4 -> 1418.344 | H4: =D4*55%+C4 -> 1559.38 | I4: =D4*89%+C4 -> 1787.724 | J4: =E4*144%+D4 -> 2510.9235 | L4: =(M4*100/C4)-100 -> 47.672269 | M4: =VLOOKUP(A4&"EQ",BhavCopy_NSE_CM!A:U,19,0) -> 1757.3 | N4: =VLOOKUP(A4&"EQ",BhavCopy_NSE_CM!A:U,21,0) -> 1711.6 | O4: =B4-M4*10% -> 1685.87 | P4: =B4-M4*20% -> 1510.14 | Q4: 2 | R4: =M4<I4 -> TRUE | S4: 1861.6 | T4: 1560-1680-1870-1960 | U4: 31.07.2026
A5: Atherenerg | B5: 1725.6 | C5: 1130 | D5: =B5-C5 -> 595.6 | E5: =D5*13%+C5 -> 1207.428 | F5: =D5*21%+C5 -> 1255.076 | G5: =D5*34%+C5 -> 1332.504 | H5: =D5*55%+C5 -> 1457.58 | I5: =D5*89%+C5 -> 1660.084 | J5: =E5*144%+D5 -> 2334.2963 | L5: =(M5*100/C5)-100 -> 39.646018 | M5: =VLOOKUP(A5&"EQ",BhavCopy_NSE_CM!A:U,19,0) -> 1578 | N5: =VLOOKUP(A5&"EQ",BhavCopy_NSE_CM!A:U,21,0) -> 1599.3 | O5: =B5-M5*10% -> 1567.8 | P5: =B5-M5*20% -> 1410 | Q5: 3 | R5: =M5<I5 -> TRUE | S5: 1616.3 | T5: 1240-1320-1860 | U5: 28.08.2026
A6: Aurionpro | B6: 1951.95 | C6: 668.7 | D6: =B6-C6 -> 1283.25 | E6: =D6*13%+C6 -> 835.5225 | F6: =D6*21%+C6 -> 938.1825 | G6: =D6*34%+C6 -> 1105.005 | H6: =D6*55%+C6 -> 1374.4875 | I6: =D6*89%+C6 -> 1810.7925 | J6: =E6*144%+D6 -> 2486.4024 | L6: =(M6*100/C6)-100 -> 0.50844923 | M6: =VLOOKUP(A6&"EQ",BhavCopy_NSE_CM!A:U,19,0) -> 672.1 | N6: =VLOOKUP(A6&"EQ",BhavCopy_NSE_CM!A:U,21,0) -> 668.7 | O6: =B6-M6*10% -> 1884.74 | P6: =B6-M6*20% -> 1817.53 | Q6: 4 | R6: =M6<I6 -> TRUE | S6: 1896.75 | T6: 725-910-960-1180
A7: Avalon | B7: 2373.3 | C7: 1320 | D7: =B7-C7 -> 1053.3 | E7: =D7*13%+C7 -> 1456.929 | F7: =D7*21%+C7 -> 1541.193 | G7: =D7*34%+C7 -> 1678.122 | H7: =D7*55%+C7 -> 1899.315 | I7: =D7*89%+C7 -> 2257.437 | J7: =E7*144%+D7 -> 3151.2778 | L7: =(M7*100/C7)-100 -> 73.507576 | M7: =VLOOKUP(A7&"EQ",BhavCopy_NSE_CM!A:U,19,0) -> 2290.3 | N7: =VLOOKUP(A7&"EQ",BhavCopy_NSE_CM!A:U,21,0) -> 2352.5 | O7: =B7-M7*10% -> 2144.27 | P7: =B7-M7*20% -> 1915.24 | Q7: 5 | R7: =M7<I7 -> FALSE | S7: 2256.6 | T7: 1480-1710-1795-2130 | U7: 28.08.2026
A8: BIRLANU | B8: 2000 | C8: 1200 | D8: =B8-C8 -> 800 | E8: =D8*13%+C8 -> 1304 | F8: =D8*21%+C8 -> 1368 | G8: =D8*34%+C8 -> 1472 | H8: =D8*55%+C8 -> 1640 | I8: =D8*89%+C8 -> 1912 | J8: =E8*144%+D8 -> 2677.76 | L8: =(M8*100/C8)-100 -> 19.433333 | M8: =VLOOKUP(A8&"EQ",BhavCopy_NSE_CM!A:U,19,0) -> 1433.2 | N8: =VLOOKUP(A8&"EQ",BhavCopy_NSE_CM!A:U,21,0) -> 1448.9 | O8: =B8-M8*10% -> 1856.68 | P8: =B8-M8*20% -> 1713.36 | Q8: 6 | R8: =M8<I8 -> TRUE | S8: 2374.1 | T8: 1340-1655-1715-1890-2040
A9: E2E | B9: 686.15 | C9: 383 | D9: =B9-C9 -> 303.15 | E9: =D9*13%+C9 -> 422.4095 | F9: =D9*21%+C9 -> 446.6615 | G9: =D9*34%+C9 -> 486.071 | H9: =D9*55%+C9 -> 549.7325 | I9: =D9*89%+C9 -> 652.8035 | J9: =E9*144%+D9 -> 911.41968 | L9: =(M9*100/C9)-100 -> 61.253264 | M9: =VLOOKUP(A9&"BE",BhavCopy_NSE_CM!A:U,19,0) -> 617.6 | N9: =VLOOKUP(A9&"BE",BhavCopy_NSE_CM!A:U,21,0) -> 630.2 | O9: =B9-M9*10% -> 624.39 | P9: =B9-M9*20% -> 562.63 | Q9: 7 | R9: =M9<I9 -> TRUE | S9: 666.75 | T9: 370-470-560-640-950 | U9: 07.08.2026
A10: Hcg | B10: 804.65 | C10: 600 | D10: =B10-C10 -> 204.65 | E10: =D10*13%+C10 -> 626.6045 | F10: =D10*21%+C10 -> 642.9765 | G10: =D10*34%+C10 -> 669.581 | H10: =D10*55%+C10 -> 712.5575 | I10: =D10*89%+C10 -> 782.1385 | J10: =E10*144%+D10 -> 1106.9605 | L10: =(M10*100/C10)-100 -> 15.1 | M10: =VLOOKUP(A10&"EQ",BhavCopy_NSE_CM!A:U,19,0) -> 690.6 | N10: =VLOOKUP(A10&"EQ",BhavCopy_NSE_CM!A:U,21,0) -> 687.9 | O10: =B10-M10*10% -> 735.59 | P10: =B10-M10*20% -> 666.53 | Q10: 8 | R10: =M10<I10 -> TRUE | S10: 725.95 | T10: 575-615-640-700-815 | U10: 21.08.2026
A11: Heg | B11: 739.25 | C11: 510 | D11: =B11-C11 -> 229.25 | E11: =D11*13%+C11 -> 539.8025 | F11: =D11*21%+C11 -> 558.1425 | G11: =D11*34%+C11 -> 587.945 | H11: =D11*55%+C11 -> 636.0875 | I11: =D11*89%+C11 -> 714.0325 | J11: =E11*144%+D11 -> 1006.5656 | L11: =(M11*100/C11)-100 -> #N/A | M11: =VLOOKUP(A11&"EQ",BhavCopy_NSE_CM!A:U,19,0) -> #N/A | N11: =VLOOKUP(A11&"EQ",BhavCopy_NSE_CM!A:U,21,0) -> #N/A | O11: =B11-M11*10% -> #N/A | P11: =B11-M11*20% -> #N/A | Q11: 9 | R11: =M11<I11 -> #N/A | S11: 739.25 | T11: 585-640-690-820-950 | U11: 28.08.2026
A12: Heritgfood | B12: 527 | C12: 296 | D12: =B12-C12 -> 231 | E12: =D12*13%+C12 -> 326.03 | F12: =D12*21%+C12 -> 344.51 | G12: =D12*34%+C12 -> 374.54 | H12: =D12*55%+C12 -> 423.05 | I12: =D12*89%+C12 -> 501.59 | J12: =E12*144%+D12 -> 700.4832 | L12: =(M12*100/C12)-100 -> 29.10473 | M12: =VLOOKUP(A12&"EQ",BhavCopy_NSE_CM!A:U,19,0) -> 382.15 | N12: =VLOOKUP(A12&"EQ",BhavCopy_NSE_CM!A:U,21,0) -> 384.15 | O12: =B12-M12*10% -> 488.785 | P12: =B12-M12*20% -> 450.57 | Q12: 10 | R12: =M12<I12 -> TRUE | S12: 661.25 | T12: 282-310-330-390-420-523
A13: Hindoilexp | B13: 285.8 | C13: 147 | D13: =B13-C13 -> 138.8 | E13: =D13*13%+C13 -> 165.044 | F13: =D13*21%+C13 -> 176.148 | G13: =D13*34%+C13 -> 194.192 | H13: =D13*55%+C13 -> 223.34 | I13: =D13*89%+C13 -> 270.532 | J13: =E13*144%+D13 -> 376.46336 | L13: =(M13*100/C13)-100 -> 31.741497 | M13: =VLOOKUP(A13&"EQ",BhavCopy_NSE_CM!A:U,19,0) -> 193.66 | N13: =VLOOKUP(A13&"EQ",BhavCopy_NSE_CM!A:U,21,0) -> 188.85 | O13: =B13-M13*10% -> 266.434 | P13: =B13-M13*20% -> 247.068 | Q13: 11 | R13: =M13<I13 -> TRUE | S13: 285.8 | T13: 132-155-190
A14: Inoxwind | B14: 161 | C14: 68 | D14: =B14-C14 -> 93 | E14: =D14*13%+C14 -> 80.09 | F14: =D14*21%+C14 -> 87.53 | G14: =D14*34%+C14 -> 99.62 | H14: =D14*55%+C14 -> 119.15 | I14: =D14*89%+C14 -> 150.77 | J14: =E14*144%+D14 -> 208.3296 | L14: =(M14*100/C14)-100 -> 11.338235 | M14: =VLOOKUP(A14&"EQ",BhavCopy_NSE_CM!A:U,19,0) -> 75.71 | N14: =VLOOKUP(A14&"EQ",BhavCopy_NSE_CM!A:U,21,0) -> 75.6 | O14: =B14-M14*10% -> 153.429 | P14: =B14-M14*20% -> 145.858 | Q14: 12 | R14: =M14<I14 -> TRUE | S14: 103.6 | T14: 68-75.8-82.25-89-95-103-118-170
A15: Jyoticnc | B15: 1370 | C15: 698 | D15: =B15-C15 -> 672 | E15: =D15*13%+C15 -> 785.36 | F15: =D15*21%+C15 -> 839.12 | G15: =D15*34%+C15 -> 926.48 | H15: =D15*55%+C15 -> 1067.6 | I15: =D15*89%+C15 -> 1296.08 | J15: =E15*144%+D15 -> 1802.9184 | L15: =(M15*100/C15)-100 -> 48.595989 | M15: =VLOOKUP(A15&"EQ",BhavCopy_NSE_CM!A:U,19,0) -> 1037.2 | N15: =VLOOKUP(A15&"EQ",BhavCopy_NSE_CM!A:U,21,0) -> 1020.65 | O15: =B15-M15*10% -> 1266.28 | P15: =B15-M15*20% -> 1162.56 | Q15: 13 | R15: =M15<I15 -> TRUE | S15: 1370
A16: Powermech | B16: 3506.35 | C16: 2261.6 | D16: =B16-C16 -> 1244.75 | E16: =D16*13%+C16 -> 2423.4175 | F16: =D16*21%+C16 -> 2522.9975 | G16: =D16*34%+C16 -> 2684.815 | H16: =D16*55%+C16 -> 2946.2125 | I16: =D16*89%+C16 -> 3369.4275 | J16: =E16*144%+D16 -> 4734.4712 | L16: =(M16*100/C16)-100 -> 6.7872303 | M16: =VLOOKUP(A16&"EQ",BhavCopy_NSE_CM!A:U,19,0) -> 2415.1 | N16: =VLOOKUP(A16&"EQ",BhavCopy_NSE_CM!A:U,21,0) -> 2359.8 | O16: =B16-M16*10% -> 3264.84 | P16: =B16-M16*20% -> 3023.33 | Q16: 14 | R16: =M16<I16 -> TRUE | S16: 3444.15 | T16: 2330-2490-2760-3030-3290
A17: Thomascook | B17: 261.9 | C17: 87.99 | D17: =B17-C17 -> 173.91 | E17: =D17*13%+C17 -> 110.5983 | F17: =D17*21%+C17 -> 124.5111 | G17: =D17*34%+C17 -> 147.1194 | H17: =D17*55%+C17 -> 183.6405 | I17: =D17*89%+C17 -> 242.7699 | J17: =E17*144%+D17 -> 333.17155 | L17: =(M17*100/C17)-100 -> 24.911922 | M17: =VLOOKUP(A17&"EQ",BhavCopy_NSE_CM!A:U,19,0) -> 109.91 | N17: =VLOOKUP(A17&"EQ",BhavCopy_NSE_CM!A:U,21,0) -> 112.52 | O17: =B17-M17*10% -> 250.909 | P17: =B17-M17*20% -> 239.918 | Q17: 15 | R17: =M17<I17 -> TRUE | S17: 257.41 | T17: 88-118-133-155
A18: Vadilalind | B18: 7900 | C18: 5770 | D18: =B18-C18 -> 2130 | E18: =D18*13%+C18 -> 6046.9 | F18: =D18*21%+C18 -> 6217.3 | G18: =D18*34%+C18 -> 6494.2 | H18: =D18*55%+C18 -> 6941.5 | I18: =D18*89%+C18 -> 7665.7 | J18: =E18*144%+D18 -> 10837.536 | L18: =(M18*100/C18)-100 -> 30.580589 | M18: =VLOOKUP(A18&"EQ",BhavCopy_NSE_CM!A:U,19,0) -> 7534.5 | N18: =VLOOKUP(A18&"EQ",BhavCopy_NSE_CM!A:U,21,0) -> 7505.5 | O18: =B18-M18*10% -> 7146.55 | P18: =B18-M18*20% -> 6393.1 | Q18: 16 | R18: =M18<I18 -> TRUE | S18: 7900 | T18: 5900-6710-7550-9700 | U18: 28.08.2026
A19: VrLlog | B19: 397.5 | C19: 225 | D19: =B19-C19 -> 172.5 | E19: =D19*13%+C19 -> 247.425 | F19: =D19*21%+C19 -> 261.225 | G19: =D19*34%+C19 -> 283.65 | H19: =D19*55%+C19 -> 319.875 | I19: =D19*89%+C19 -> 378.525 | J19: =E19*144%+D19 -> 528.792 | L19: =(M19*100/C19)-100 -> 30.555556 | M19: =VLOOKUP(A19&"EQ",BhavCopy_NSE_CM!A:U,19,0) -> 293.75 | N19: =VLOOKUP(A19&"EQ",BhavCopy_NSE_CM!A:U,21,0) -> 292.75 | O19: =B19-M19*10% -> 368.125 | P19: =B19-M19*20% -> 338.75 | Q19: 17 | R19: =M19<I19 -> TRUE | S19: 391.3 | T19: 255-299-316-332-400
A20: Zentec | B20: 2577 | C20: 1510 | D20: =B20-C20 -> 1067 | E20: =D20*13%+C20 -> 1648.71 | F20: =D20*21%+C20 -> 1734.07 | G20: =D20*34%+C20 -> 1872.78 | H20: =D20*55%+C20 -> 2096.85 | I20: =D20*89%+C20 -> 2459.63 | J20: =E20*144%+D20 -> 3441.1424 | L20: =(M20*100/C20)-100 -> 20.860927 | M20: =VLOOKUP(A20&"EQ",BhavCopy_NSE_CM!A:U,19,0) -> 1825 | N20: =VLOOKUP(A20&"EQ",BhavCopy_NSE_CM!A:U,21,0) -> 1794.6 | O20: =B20-M20*10% -> 2394.5 | P20: =B20-M20*20% -> 2212 | Q20: 18 | R20: =M20<I20 -> TRUE | S20: 2533.45 | T20: 1300-1580-1850-2035-2400-2740
G21: =D21*34%+C21 -> 0
A22: NIFTY FNO STOCKS | D22: =B22-C22 -> 0 | E22: =D22*13%+C22 -> 0 | F22: =D22*21%+C22 -> 0 | G22: =D22*34%+C22 -> 0 | H22: =D22*55%+C22 -> 0 | I22: =D22*89%+C22 -> 0
A23: 360ONE | B23: 1236.2 | C23: 906.05 | D23: =B23-C23 -> 330.15 | E23: =D23*13%+C23 -> 948.9695 | F23: =D23*21%+C23 -> 975.3815 | G23: =D23*34%+C23 -> 1018.301 | H23: =D23*55%+C23 -> 1087.6325 | I23: =D23*89%+C23 -> 1199.8835 | J23: =E23*144%+D23 -> 1696.6661 | L23: =(M23*100/C23)-100 -> 22.509795 | M23: =VLOOKUP(A23&"EQ",BhavCopy_NSE_CM!A:U,19,0) -> 1110 | N23: =VLOOKUP(A23&"EQ",BhavCopy_NSE_CM!A:U,21,0) -> 1136.9 | O23: =B23-M23*10% -> 1125.2 | P23: =B23-M23*20% -> 1014.2 | Q23: 1 | R23: =M23<I23 -> TRUE
A24: ABB | B24: 7924.5 | C24: 4637.5 | D24: =B24-C24 -> 3287 | E24: =D24*13%+C24 -> 5064.81 | F24: =D24*21%+C24 -> 5327.77 | G24: =D24*34%+C24 -> 5755.08 | H24: =D24*55%+C24 -> 6445.35 | I24: =D24*89%+C24 -> 7562.93 | J24: =E24*144%+D24 -> 10580.326 | L24: =(M24*100/C24)-100 -> 59.28841 | M24: =VLOOKUP(A24&"EQ",BhavCopy_NSE_CM!A:U,19,0) -> 7387 | N24: =VLOOKUP(A24&"EQ",BhavCopy_NSE_CM!A:U,21,0) -> 7434 | O24: =B24-M24*10% -> 7185.8 | P24: =B24-M24*20% -> 6447.1 | Q24: 2 | R24: =M24<I24 -> TRUE
A25: ABCAPITAL | B25: 424.7 | C25: 243 | D25: =B25-C25 -> 181.7 | E25: =D25*13%+C25 -> 266.621 | F25: =D25*21%+C25 -> 281.157 | G25: =D25*34%+C25 -> 304.778 | H25: =D25*55%+C25 -> 342.935 | I25: =D25*89%+C25 -> 404.713 | J25: =E25*144%+D25 -> 565.63424 | L25: =(M25*100/C25)-100 -> 63.353909 | M25: =VLOOKUP(A25&"EQ",BhavCopy_NSE_CM!A:U,19,0) -> 396.95 | N25: =VLOOKUP(A25&"EQ",BhavCopy_NSE_CM!A:U,21,0) -> 403.25 | O25: =B25-M25*10% -> 385.005 | P25: =B25-M25*20% -> 345.31 | Q25: 3 | R25: =M25<I25 -> TRUE
A26: ADANIENSOL | B26: 1744 | C26: 744.9 | D26: =B26-C26 -> 999.1 | E26: =D26*13%+C26 -> 874.783 | F26: =D26*21%+C26 -> 954.711 | G26: =D26*34%+C26 -> 1084.594 | H26: =D26*55%+C26 -> 1294.405 | I26: =D26*89%+C26 -> 1634.099 | J26: =E26*144%+D26 -> 2258.7875 | L26: =(M26*100/C26)-100 -> 88.978386 | M26: =VLOOKUP(A26&"EQ",BhavCopy_NSE_CM!A:U,19,0) -> 1407.7 | N26: =VLOOKUP(A26&"EQ",BhavCopy_NSE_CM!A:U,21,0) -> 1390.4 | O26: =B26-M26*10% -> 1603.23 | P26: =B26-M26*20% -> 1462.46 | Q26: 4 | R26: =M26<I26 -> TRUE
A27: ADANIENT | B27: 3245 | C27: 1753 | D27: =B27-C27 -> 1492 | E27: =D27*13%+C27 -> 1946.96 | F27: =D27*21%+C27 -> 2066.32 | G27: =D27*34%+C27 -> 2260.28 | H27: =D27*55%+C27 -> 2573.6 | I27: =D27*89%+C27 -> 3080.88 | J27: =E27*144%+D27 -> 4295.6224 | L27: =(M27*100/C27)-100 -> 68.459783 | M27: =VLOOKUP(A27&"EQ",BhavCopy_NSE_CM!A:U,19,0) -> 2953.1 | N27: =VLOOKUP(A27&"EQ",BhavCopy_NSE_CM!A:U,21,0) -> 2950 | O27: =B27-M27*10% -> 2949.69 | P27: =B27-M27*20% -> 2654.38 | Q27: 5 | R27: =M27<I27 -> TRUE
A28: ADANIGREEN | B28: 1631.5 | C28: 765 | D28: =B28-C28 -> 866.5 | E28: =D28*13%+C28 -> 877.645 | F28: =D28*21%+C28 -> 946.965 | G28: =D28*34%+C28 -> 1059.61 | H28: =D28*55%+C28 -> 1241.575 | I28: =D28*89%+C28 -> 1536.185 | J28: =E28*144%+D28 -> 2130.3088 | L28: =(M28*100/C28)-100 -> 68.888889 | M28: =VLOOKUP(A28&"EQ",BhavCopy_NSE_CM!A:U,19,0) -> 1292 | N28: =VLOOKUP(A28&"EQ",BhavCopy_NSE_CM!A:U,21,0) -> 1288 | O28: =B28-M28*10% -> 1502.3 | P28: =B28-M28*20% -> 1373.1 | Q28: 6 | R28: =M28<I28 -> TRUE
A29: ADANIPORTS | B29: 1891.1 | C29: 1290.5 | D29: =B29-C29 -> 600.6 | E29: =D29*13%+C29 -> 1368.578 | F29: =D29*21%+C29 -> 1416.626 | G29: =D29*34%+C29 -> 1494.704 | H29: =D29*55%+C29 -> 1620.83 | I29: =D29*89%+C29 -> 1825.034 | J29: =E29*144%+D29 -> 2571.3523 | L29: =(M29*100/C29)-100 -> 32.50678 | M29: =VLOOKUP(A29&"EQ",BhavCopy_NSE_CM!A:U,19,0) -> 1710 | N29: =VLOOKUP(A29&"EQ",BhavCopy_NSE_CM!A:U,21,0) -> 1694.3 | O29: =B29-M29*10% -> 1720.1 | P29: =B29-M29*20% -> 1549.1 | Q29: 7 | R29: =M29<I29 -> TRUE
A30: ADANIPOWER | B30: 723 | C30: 128.1 | D30: =B30-C30 -> 594.9 | E30: =D30*13%+C30 -> 205.437 | F30: =D30*21%+C30 -> 253.029 | G30: =D30*34%+C30 -> 330.366 | H30: =D30*55%+C30 -> 455.295 | I30: =D30*89%+C30 -> 657.561 | J30: =E30*144%+D30 -> 890.72928 | L30: =(M30*100/C30)-100 -> 62.685402 | M30: =VLOOKUP(A30&"EQ",BhavCopy_NSE_CM!A:U,19,0) -> 208.4 | N30: =VLOOKUP(A30&"EQ",BhavCopy_NSE_CM!A:U,21,0) -> 204.49 | O30: =B30-M30*10% -> 702.16 | P30: =B30-M30*20% -> 681.32 | Q30: 8 | R30: =M30<I30 -> TRUE
A31: ALKEM | B31: 5933.5 | C31: 4738.5 | D31: =B31-C31 -> 1195 | E31: =D31*13%+C31 -> 4893.85 | F31: =D31*21%+C31 -> 4989.45 | G31: =D31*34%+C31 -> 5144.8 | H31: =D31*55%+C31 -> 5395.75 | I31: =D31*89%+C31 -> 5802.05 | J31: =E31*144%+D31 -> 8242.144 | L31: =(M31*100/C31)-100 -> 9.3383982 | M31: =VLOOKUP(A31&"EQ",BhavCopy_NSE_CM!A:U,19,0) -> 5181 | N31: =VLOOKUP(A31&"EQ",BhavCopy_NSE_CM!A:U,21,0) -> 5242.5 | O31: =B31-M31*10% -> 5415.4 | P31: =B31-M31*20% -> 4897.3 | Q31: 9 | R31: =M31<I31 -> TRUE
A32: AMBER | B32: 8974 | C32: 5400.5 | D32: =B32-C32 -> 3573.5 | E32: =D32*13%+C32 -> 5865.055 | F32: =D32*21%+C32 -> 6150.935 | G32: =D32*34%+C32 -> 6615.49 | H32: =D32*55%+C32 -> 7365.925 | I32: =D32*89%+C32 -> 8580.915 | J32: =E32*144%+D32 -> 12019.179 | L32: =(M32*100/C32)-100 -> 35.320804 | M32: =VLOOKUP(A32&"EQ",BhavCopy_NSE_CM!A:U,19,0) -> 7308 | N32: =VLOOKUP(A32&"EQ",BhavCopy_NSE_CM!A:U,21,0) -> 7439 | O32: =B32-M32*10% -> 8243.2 | P32: =B32-M32*20% -> 7512.4 | Q32: 10 | R32: =M32<I32 -> TRUE
A33: AMBUJACEM | B33: 624.95 | C33: 394 | D33: =B33-C33 -> 230.95 | E33: =D33*13%+C33 -> 424.0235 | F33: =D33*21%+C33 -> 442.4995 | G33: =D33*34%+C33 -> 472.523 | H33: =D33*55%+C33 -> 521.0225 | I33: =D33*89%+C33 -> 599.5455 | J33: =E33*144%+D33 -> 841.54384 | L33: =(M33*100/C33)-100 -> 1.0913706 | M33: =VLOOKUP(A33&"EQ",BhavCopy_NSE_CM!A:U,19,0) -> 398.3 | N33: =VLOOKUP(A33&"EQ",BhavCopy_NSE_CM!A:U,21,0) -> 398.6 | O33: =B33-M33*10% -> 585.12 | P33: =B33-M33*20% -> 545.29 | Q33: 11 | R33: =M33<I33 -> TRUE
A34: ANGELONE | B34: 2872 | C34: 208.63 | D34: =B34-C34 -> 2663.37 | E34: =D34*13%+C34 -> 554.8681 | F34: =D34*21%+C34 -> 767.9377 | G34: =D34*34%+C34 -> 1114.1758 | H34: =D34*55%+C34 -> 1673.4835 | I34: =D34*89%+C34 -> 2579.0293 | J34: =E34*144%+D34 -> 3462.3801 | L34: =(M34*100/C34)-100 -> 42.836601 | M34: =VLOOKUP(A34&"EQ",BhavCopy_NSE_CM!A:U,19,0) -> 298 | N34: =VLOOKUP(A34&"EQ",BhavCopy_NSE_CM!A:U,21,0) -> 303.8 | O34: =B34-M34*10% -> 2842.2 | P34: =B34-M34*20% -> 2812.4 | Q34: 12 | R34: =M34<I34 -> TRUE
... A231: ZYDUSLIFE | B231: 1205 | C231: 835.5 | D231: =B231-C231 -> 369.5 | E231: =D231*13%+C231 -> 883.535 | F231: =D231*21%+C231 -> 913.095 | G231: =D231*34%+C231 -> 961.13 | H231: =D231*55%+C231 -> 1038.725 | I231: =D231*89%+C231 -> 1164.355 | J231: =E231*144%+D231 -> 1641.7904 | L231: =(M231*100/C231)-100 -> 37.103531 | M231: =VLOOKUP(A231&"EQ",BhavCopy_NSE_CM!A:U,19,0) -> 1145.5 | N231: =VLOOKUP(A231&"EQ",BhavCopy_NSE_CM!A:U,21,0) -> 1156.9 | O231: =B231-M231*10% -> 1090.45 | P231: =B231-M231*20% -> 975.9 | Q231: 209 | R231: =M231<I231 -> TRUE
