Workbook

Sheet cmbhavcopy
A1: TradDt | B1: BizDt | C1: Sgmt | D1: Src | E1: FinInstrmTp | F1: FinInstrmId | G1: ISIN | H1: TckrSymb | I1: SctySrs | J1: XpryDt | K1: FininstrmActlXpryDt | L1: StrkPric | M1: OptnTp | N1: FinInstrmNm | O1: OpnPric | P1: HghPric | Q1: LwPric | R1: ClsPric | S1: LastPric | T1: PrvsClsgPric | U1: UndrlygPric | V1: SttlmPric | W1: OpnIntrst | X1: ChngInOpnIntrst | Y1: TtlTradgVol | Z1: TtlTrfVal | AA1: TtlNbOfTxsExctd | AB1: SsnId | AC1: NewBrdLotQty | AD1: Rmks | AE1: Rsvd1 | AF1: Rsvd2 | AG1: Rsvd3 | AH1: Rsvd4
A2: 46273 | B2: 46273 | C2: CM | D2: NSE | E2: STK | F2: 19078 | G2: IN0020200104 | H2: SGBJUN28 | I2: GB | N2: 2.5%GOLDBONDS2028SR-III | O2: 15116.04 | P2: 15195.03 | Q2: 15070 | R2: 15070 | S2: 15070 | T2: 15085.7 | V2: 15070 | Y2: 149 | Z2: 2251747.5 | AA2: 34 | AB2: F1 | AC2: 1
A3: 46273 | B3: 46273 | C3: CM | D3: NSE | E3: STK | F3: 1342 | G3: IN0020200286 | H3: SGBN28VIII | I3: GB | N3: 2.5%GOLDBONDS2028SR-VIII | O3: 15157 | P3: 15246 | Q3: 15052 | R3: 15124.99 | S3: 15124.99 | T3: 15095.19 | V3: 15124.99 | Y3: 60 | Z3: 908678.92 | AA3: 24 | AB3: F1 | AC3: 1
A4: 46273 | B4: 46273 | C4: CM | D4: NSE | E4: STK | F4: 3742 | G4: IN0020210053 | H4: SGBMAY29I | I4: GB | N4: 2.5%GOLDBONDS2029SR-I | O4: 15017.56 | P4: 15224.99 | Q4: 15016 | R4: 15139.28 | S4: 15180 | T4: 15093.03 | V4: 15138.2 | Y4: 446 | Z4: 6763741.6 | AA4: 60 | AB4: F1 | AC4: 1
A5: 46273 | B5: 46273 | C5: CM | D5: NSE | E5: STK | F5: 3743 | G5: IN0020210061 | H5: SGBJUN29II | I5: GB | N5: 2.5%GOLDBONDS2029SR-II | O5: 15025 | P5: 15188 | Q5: 15025 | R5: 15068.84 | S5: 15063 | T5: 15090 | V5: 15074.5 | Y5: 43 | Z5: 650755.89 | AA5: 21 | AB5: F1 | AC5: 1
A6: 46273 | B6: 46273 | C6: CM | D6: NSE | E6: STK | F6: 3800 | G6: IN0020210087 | H6: SGBJU29III | I6: GB | N6: 2.5%GOLDBONDS2029SR-III | O6: 15015.01 | P6: 15349 | Q6: 15015.01 | R6: 15067.37 | S6: 15067.37 | T6: 15079.88 | V6: 15067.37 | Y6: 52 | Z6: 786679.41 | AA6: 27 | AB6: F1 | AC6: 1
A7: 46273 | B7: 46273 | C7: CM | D7: NSE | E7: STK | F7: 5575 | G7: IN0020210145 | H7: SGBSEP29VI | I7: GB | N7: 2.5%GOLDBONDS2029SR-VI | O7: 15101 | P7: 15389 | Q7: 15012 | R7: 15052.16 | S7: 15060 | T7: 15037.44 | V7: 15046.34 | Y7: 126 | Z7: 1904401.7 | AA7: 45 | AB7: F1 | AC7: 1
A8: 46273 | B8: 46273 | C8: CM | D8: NSE | E8: STK | F8: 6518 | G8: IN0020210178 | H8: SGBNV29VII | I8: GB | N8: 2.5%GOLDBONDS2029SR-VII | O8: 15151 | P8: 15289 | Q8: 15100.33 | R8: 15118.29 | S8: 15150 | T8: 15100.33 | V8: 15098 | Y8: 50 | Z8: 757623.33 | AA8: 16 | AB8: F1 | AC8: 1
A9: 46273 | B9: 46273 | C9: CM | D9: NSE | E9: STK | F9: 5960 | G9: IN0020180249 | H9: SGBOCT26 | I9: GB | N9: 2.50%GOLDBONDS2026SR-II | O9: 15150 | P9: 15150 | Q9: 15150 | R9: 15150 | S9: 15150 | T9: 15000 | V9: 15150 | Y9: 1 | Z9: 15150 | AA9: 1 | AB9: F1 | AC9: 1
A10: 46273 | B10: 46273 | C10: CM | D10: NSE | E10: STK | F10: 7654 | G10: IN0020180389 | H10: SGBDEC26 | I10: GB | N10: 2.50%GOLDBONDS2026SR-IV | O10: 15100.01 | P10: 15100.01 | Q10: 15100.01 | R10: 15100.01 | S10: 15100.01 | T10: 15100.9 | V10: 15100.01 | Y10: 1 | Z10: 15100.01 | AA10: 1 | AB10: F1 | AC10: 1
A11: 46273 | B11: 46273 | C11: CM | D11: NSE | E11: STK | F11: 10261 | G11: IN0020190073 | H11: SGBJUN27 | I11: GB | N11: 2.50%GOLDBONDS2027SR-I | O11: 15000 | P11: 15100 | Q11: 15000 | R11: 15056.83 | S11: 15050 | T11: 15045.45 | V11: 15056.83 | Y11: 70 | Z11: 1053079 | AA11: 17 | AB11: F1 | AC11: 1
A12: 46273 | B12: 46273 | C12: CM | D12: NSE | E12: STK | F12: 11154 | G12: IN0020190081 | H12: SGBJUL27 | I12: GB | N12: 2.50%GOLDBONDS2027SR-II | O12: 15025.5 | P12: 15025.5 | Q12: 15001 | R12: 15001 | S12: 15001 | T12: 14911.02 | V12: 15001 | Y12: 2 | Z12: 30026.5 | AA12: 2 | AB12: F1 | AC12: 1
A13: 46273 | B13: 46273 | C13: CM | D13: NSE | E13: STK | F13: 12904 | G13: IN0020190107 | H13: SGBAUG27 | I13: GB | N13: 2.50%GOLDBONDS2027SR-III | O13: 15101 | P13: 15120 | Q13: 15066.54 | R13: 15070.25 | S13: 15066.54 | T13: 15066.54 | V13: 15074.16 | Y13: 69 | Z13: 1041522.5 | AA13: 16 | AB13: F1 | AC13: 1
... A1482: 46273 | B1482: 46273 | C1482: CM | D1482: NSE | E1482: STK | F1482: 17140 | G1482: INE349Y01013 | H1482: IDEAFORGE | I1482: EQ | N1482: IDEAFORGE TECHNO LTD | O1482: 771 | P1482: 799 | Q1482: 771 | R1482: 775.2 | S1482: 777 | T1482: 765.45 | V1482: 775.22 | Y1482: 409710 | Z1482: 3.2164114e+08 | AA1482: 21103 | AB1482: F1 | AC1482: 1
A1483: 46273 | B1483: 46273 | C1483: CM | D1483: NSE | E1483: STK | F1483: 28574 | G1483: INE0TD101011 | H1483: IDENTICAL | I1483: SM | N1483: IDENTICAL BRAINS STUDIO L | O1483: 17.45 | P1483: 19.7 | Q1483: 17.45 | R1483: 19.7 | S1483: 19.7 | T1483: 18.05 | V1483: 19.7 | Y1483: 12000 | Z1483: 231900 | AA1483: 5 | AB1483: F1 | AC1483: 2000 | AI1483: 46044 | AJ1483: CM | AK1483: NSE | AL1483: STK | AM1483: 6600 | AN1483: INE949P01018 | AO1483: GENUSPAPER | AP1483: EQ | AU1483: GENUS P&B LIMITED | AV1483: 12.05 | AW1483: 12.39 | AX1483: 12 | AY1483: 12.21 | AZ1483: 12.13 | BA1483: 12.2 | BC1483: 12.22 | BF1483: 58058 | BG1483: 706170.61 | BH1483: 355 | BI1483: F1 | BJ1483: 1
A1484: 46273 | B1484: 46273 | C1484: CM | D1484: NSE | E1484: STK | F1484: 11184 | G1484: INE092T01019 | H1484: IDFCFIRSTB | I1484: EQ | N1484: IDFC FIRST BANK LIMITED | O1484: 86.44 | P1484: 87.1 | Q1484: 86.02 | R1484: 86.5 | S1484: 86.5 | T1484: 86.44 | V1484: 86.49 | Y1484: 11728338 | Z1484: 1.0169257e+09 | AA1484: 45304 | AB1484: F1 | AC1484: 1
A1485: 46273 | B1485: 46273 | C1485: CM | D1485: NSE | E1485: STK | F1485: 1482 | G1485: INE076C01018 | H1485: IFBAGRO | I1485: EQ | N1485: IFB AGRO INDUSTRIES LTD | O1485: 914.2 | P1485: 914.2 | Q1485: 884.05 | R1485: 887.05 | S1485: 888 | T1485: 896.25 | V1485: 887.02 | Y1485: 3184 | Z1485: 2831115 | AA1485: 229 | AB1485: F1 | AC1485: 1
A1486: 46273 | B1486: 46273 | C1486: CM | D1486: NSE | E1486: STK | F1486: 1485 | G1486: INE559A01017 | H1486: IFBIND | I1486: EQ | N1486: IFB INDUSTRIES LTD | O1486: 1314 | P1486: 1314.9 | Q1486: 1290 | R1486: 1296 | S1486: 1297 | T1486: 1313.6 | V1486: 1296.11 | Y1486: 30359 | Z1486: 39514590 | AA1486: 2655 | AB1486: F1 | AC1486: 1
A1487: 46273 | B1487: 46273 | C1487: CM | D1487: NSE | E1487: STK | F1487: 1491 | G1487: INE039A01010 | H1487: IFCI | I1487: EQ | N1487: IFCI LTD | O1487: 103.4 | P1487: 103.59 | Q1487: 91.77 | R1487: 92.61 | S1487: 92.25 | T1487: 102.51 | V1487: 92.61 | Y1487: 217424506 | Z1487: 2.0625208e+10 | AA1487: 533974 | AB1487: F1 | AC1487: 1
A1488: 46273 | B1488: 46273 | C1488: CM | D1488: NSE | E1488: STK | F1488: 436 | G1488: INE133Y01011 | H1488: IFGLEXPOR | I1488: EQ | N1488: IFGL REFRACTORIES LIMITED | O1488: 203.97 | P1488: 205.56 | Q1488: 195 | R1488: 198.22 | S1488: 199.5 | T1488: 203.79 | V1488: 198.25 | Y1488: 36372 | Z1488: 7253585.1 | AA1488: 1835 | AB1488: F1 | AC1488: 1 | AI1488: 46044 | AJ1488: CM | AK1488: NSE | AL1488: STK | AM1488: 1289 | AN1488: INE538A01037 | AO1488: GFLLIMITED | AP1488: EQ | AU1488: GFL LIMITED | AV1488: 48.88 | AW1488: 50.93 | AX1488: 48.88 | AY1488: 50 | AZ1488: 49.75 | BA1488: 48.88 | BC1488: 50 | BF1488: 47376 | BG1488: 2372023.6 | BH1488: 734 | BI1488: F1 | BJ1488: 1
A1489: 46273 | B1489: 46273 | C1489: CM | D1489: NSE | E1489: STK | F1489: 759897 | G1489: INE01XO07017 | H1489: 1225IFL27 | I1489: N0 | N1489: IFL 12.25% 2027 | O1489: 6119.25 | P1489: 6119.25 | Q1489: 6011 | R1489: 6011 | S1489: 6011 | T1489: 6119.25 | V1489: 6011 | Y1489: 2 | Z1489: 12130.25 | AA1489: 2 | AB1489: F1 | AC1489: 1
A1490: 46273 | B1490: 46273 | C1490: CM | D1490: NSE | E1490: STK | F1490: 760656 | G1490: INE01XO07025 | H1490: 1225IFL28 | I1490: N0 | N1490: IFL 12.25% 2028 | O1490: 7480 | P1490: 7505 | Q1490: 7480 | R1490: 7505 | S1490: 7505 | T1490: 7480 | V1490: 7505 | Y1490: 2 | Z1490: 14985 | AA1490: 2 | AB1490: F1 | AC1490: 1
A1491: 46273 | B1491: 46273 | C1491: CM | D1491: NSE | E1491: STK | F1491: 634 | G1491: INE188B01013 | H1491: IGARASHI | I1491: EQ | N1491: IGARASHI MOTORS INDIA LTD | O1491: 412.05 | P1491: 417.5 | Q1491: 412.05 | R1491: 415.6 | S1491: 415 | T1491: 415.15 | V1491: 415.64 | Y1491: 27204 | Z1491: 11300645 | AA1491: 1090 | AB1491: F1 | AC1491: 1
A1492: 46273 | B1492: 46273 | C1492: CM | D1492: NSE | E1492: STK | F1492: 761118 | G1492: INE530B07633 | H1492: 865IIFL31 | I1492: Y6 | N1492: IIFL 8.65% TR I SR III | O1492: 985.2 | P1492: 988 | Q1492: 985.2 | R1492: 988 | S1492: 988 | T1492: 985.2 | V1492: 988 | Y1492: 80 | Z1492: 78886 | AA1492: 4 | AB1492: F1 | AC1492: 1
A1493: 46273 | B1493: 46273 | C1493: CM | D1493: NSE | E1493: STK | F1493: 761120 | G1493: INE530B07575 | H1493: 885IIFL29 | I1493: Y8 | N1493: IIFL 8.85% TR I SR V | O1493: 1057.27 | P1493: 1057.27 | Q1493: 1020 | R1493: 1020 | S1493: 1020 | T1493: 1005 | V1493: 1023 | Y1493: 95 | Z1493: 99695.25 | AA1493: 3 | AB1493: F1 | AC1493: 1
A1494: 46273 | B1494: 46273 | C1494: CM | D1494: NSE | E1494: STK | F1494: 13072 | G1494: INE489L01022 | H1494: IIFLCAPS | I1494: EQ | N1494: IIFL CAPITAL SERVICES LTD | O1494: 341.95 | P1494: 341.95 | Q1494: 339 | R1494: 339.4 | S1494: 339.05 | T1494: 340.45 | V1494: 339.4 | Y1494: 419363 | Z1494: 142754739 | AA1494: 9240 | AB1494: F1 | AC1494: 1
A1495: 46273 | B1495: 46273 | C1495: CM | D1495: NSE | E1495: STK | F1495: 11809 | G1495: INE530B01024 | H1495: IIFL | I1495: EQ | N1495: IIFL FINANCE LIMITED | O1495: 660.2 | P1495: 675.8 | Q1495: 616.4 | R1495: 628 | S1495: 626.3 | T1495: 654.05 | V1495: 627.96 | Y1495: 6784526 | Z1495: 4.3683564e+09 | AA1495: 134174 | AB1495: F1 | AC1495: 1
A1496: 46273 | B1496: 46273 | C1496: CM | D1496: NSE | E1496: STK | F1496: 761122 | G1496: INE530B07583 | H1496: IIFL060326 | I1496: YA | N1496: IIFL TR I SR VII | O1496: 1020 | P1496: 1020 | Q1496: 1020 | R1496: 1020 | S1496: 1020 | T1496: 1019 | V1496: 1020 | Y1496: 50 | Z1496: 51000 | AA1496: 2 | AB1496: F1 | AC1496: 1
A1497: 46273 | B1497: 46273 | C1497: CM | D1497: NSE | E1497: STK | F1497: 16822 | G1497: INE0LOJ01019 | H1497: IKIO | I1497: EQ | N1497: IKIO TECHNOLOGIES LIMITED | O1497: 202 | P1497: 226.78 | Q1497: 201.98 | R1497: 219.73 | S1497: 220 | T1497: 202.98 | V1497: 219.73 | Y1497: 2263360 | Z1497: 4.9703278e+08 | AA1497: 32519 | AB1497: F1 | AC1497: 1
A1498: 46273 | B1498: 46273 | C1498: CM | D1498: NSE | E1498: STK | F1498: 9380 | G1498: INE369I01014 | H1498: IL&FSENGG | I1498: BZ | N1498: IL&FS ENG AND CONS CO LTD | O1498: 35.25 | P1498: 36.85 | Q1498: 35.25 | R1498: 36 | S1498: 36 | T1498: 37 | V1498: 36 | Y1498: 8080 | Z1498: 293240.17 | AA1498: 36 | AB1498: F1 | AC1498: 1 | AI1498: 46044 | AJ1498: CM | AK1498: NSE | AL1498: STK | AM1498: 477 | AN1498: INE800A01015 | AO1498: BIRLACABLE | AP1498: EQ | AU1498: BIRLA CABLE LIMITED | AV1498: 128.8 | AW1498: 128.8 | AX1498: 124.1 | AY1498: 125.81 | AZ1498: 125.01 | BA1498: 124.71 | BC1498: 125.75 | BF1498: 17734 | BG1498: 2254237 | BH1498: 415 | BI1498: F1 | BJ1498: 1
A1499: 46273 | B1499: 46273 | C1499: CM | D1499: NSE | E1499: STK | F1499: 6711 | G1499: INE050B01023 | H1499: IVC | I1499: EQ | N1499: IL&FS INVESTMENT MANAGERS | O1499: 10.25 | P1499: 10.38 | Q1499: 9.82 | R1499: 10.02 | S1499: 10.03 | T1499: 10.28 | V1499: 10.13 | Y1499: 1180267 | Z1499: 11887430 | AA1499: 2215 | AB1499: F1 | AC1499: 1
A1500: 46273 | B1500: 46273 | C1500: CM | D1500: NSE | E1500: STK | F1500: 9381 | G1500: INE975G01012 | H1500: IL&FSTRANS | I1500: BZ | N1500: IL&FS TRANS NET LTD | O1500: 2.11 | P1500: 2.15 | Q1500: 2.06 | R1500: 2.08 | S1500: 2.08 | T1500: 2.11 | V1500: 2.08 | Y1500: 15373 | Z1500: 32267.36 | AA1500: 47 | AB1500: F1 | AC1500: 1
A1501: 46273 | B1501: 46273 | C1501: CM | D1501: NSE | E1501: STK | F1501: 7672 | G1501: INE172N01012 | H1501: IMAGICAA | I1501: EQ | N1501: IMAGICAAWORLD ENT LTD | O1501: 56.5 | P1501: 56.51 | Q1501: 54.3 | R1501: 54.43 | S1501: 54.9 | T1501: 54.86 | V1501: 54.43 | Y1501: 653308 | Z1501: 35875936 | AA1501: 3289 | AB1501: F1 | AC1501: 1 | AI1501: 46044 | AJ1501: CM | AK1501: NSE | AL1501: STK | AM1501: 1186 | AN1501: INE068V01023 | AO1501: GLAND | AP1501: EQ | AU1501: GLAND PHARMA LIMITED | AV1501: 1714.8 | AW1501: 1728.1 | AX1501: 1693 | AY1501: 1723.3 | AZ1501: 1705 | BA1501: 1692.6 | BC1501: 1723.25 | BF1501: 54244 | BG1501: 92859469 | BH1501: 10204 | BI1501: F1 | BJ1501: 1
A1502: 46273 | B1502: 46273 | C1502: CM | D1502: NSE | E1502: STK | F1502: 25881 | G1502: INE691G01015 | H1502: IMPEXFERRO | I1502: BZ | N1502: IMPEX FERRO TECH LIMITED | O1502: 4.9 | P1502: 4.9 | Q1502: 4.9 | R1502: 4.9 | S1502: 4.9 | T1502: 4.81 | V1502: 5.03 | Y1502: 52111 | Z1502: 255343.9 | AA1502: 19 | AB1502: F1 | AC1502: 1
A1503: 46273 | B1503: 46273 | C1503: CM | D1503: NSE | E1503: STK | F1503: 17507 | G1503: INE452L01012 | H1503: INCREDIBLE | I1503: EQ | N1503: INCREDIBLE INDUSTRIES LTD | O1503: 32.48 | P1503: 32.48 | Q1503: 31.31 | R1503: 31.78 | S1503: 31.51 | T1503: 32.34 | V1503: 31.72 | Y1503: 2176 | Z1503: 69052.84 | AA1503: 78 | AB1503: F1 | AC1503: 1
A1504: 46273 | B1504: 46273 | C1504: CM | D1504: NSE | E1504: STK | F1504: 12009 | G1504: INE547E01014 | H1504: IMPAL | I1504: EQ | N1504: IND MOTOR PART & ACC LTD | O1504: 1130.9 | P1504: 1170 | Q1504: 1090.5 | R1504: 1151.5 | S1504: 1120 | T1504: 1114.2 | V1504: 1151.07 | Y1504: 15807 | Z1504: 17889472 | AA1504: 932 | AB1504: F1 | AC1504: 1
A1505: 46273 | B1505: 46273 | C1505: CM | D1505: NSE | E1505: STK | F1505: 4870 | G1505: INE915B01019 | H1505: INDSWFTLAB | I1505: EQ | N1505: IND SWIFT LABORATORIES LT | O1505: 368.7 | P1505: 401.45 | Q1505: 368.7 | R1505: 388.3 | S1505: 389 | T1505: 368.7 | V1505: 388.3 | Y1505: 2095086 | Z1505: 8.2102166e+08 | AA1505: 35895 | AB1505: F1 | AC1505: 1
A1506: 46273 | B1506: 46273 | C1506: CM | D1506: NSE | E1506: STK | F1506: 21957 | G1506: INE611L01021 | H1506: INDTERRAIN | I1506: EQ | N1506: IND TERRAIN FASHIONS LTD | O1506: 30 | P1506: 30.45 | Q1506: 30 | R1506: 30.3 | S1506: 30.37 | T1506: 30.74 | V1506: 30.3 | Y1506: 10452 | Z1506: 315862 | AA1506: 76 | AB1506: F1 | AC1506: 1
A1507: 46273 | B1507: 46273 | C1507: CM | D1507: NSE | E1507: STK | F1507: 16933 | G1507: INE841B01017 | H1507: INDBANK | I1507: EQ | N1507: INDBANK MERCH BANK | O1507: 28.68 | P1507: 28.68 | Q1507: 27.6 | R1507: 27.69 | S1507: 27.63 | T1507: 28.16 | V1507: 27.69 | Y1507: 60876 | Z1507: 1701430.3 | AA1507: 623 | AB1507: F1 | AC1507: 1
A1508: 46273 | B1508: 46273 | C1508: CM | D1508: NSE | E1508: STK | F1508: 29678 | G1508: INE0O9T01021 | H1508: BAJAJINDEF | I1508: EQ | N1508: INDEF MANUFACTURING LTD | O1508: 225.6 | P1508: 226.89 | Q1508: 220.02 | R1508: 220.95 | S1508: 222.38 | T1508: 222.26 | V1508: 220.95 | Y1508: 7155 | Z1508: 1587181.2 | AA1508: 249 | AB1508: F1 | AC1508: 1 | AI1508: 46044 | AJ1508: CM | AK1508: NSE | AL1508: STK | AM1508: 13987 | AN1508: INF209KB17D5 | AO1508: ABSLBANETF | AP1508: EQ | AU1508: BIRLASLAMC - ABSLBANETF | AV1508: 60.84 | AW1508: 60.85 | AX1508: 60.09 | AY1508: 60.47 | AZ1508: 60.46 | BA1508: 60.06 | BC1508: 60.47 | BF1508: 79501 | BG1508: 4793551.8 | BH1508: 309 | BI1508: F1 | BJ1508: 1
A1509: 46273 | B1509: 46273 | C1509: CM | D1509: NSE | E1509: STK | F1509: 23693 | G1509: INE065X01017 | H1509: INDGN | I1509: EQ | N1509: INDEGENE LIMITED | O1509: 597 | P1509: 603.6 | Q1509: 579.2 | R1509: 589.2 | S1509: 591 | T1509: 599.35 | V1509: 589.18 | Y1509: 410036 | Z1509: 2.4149508e+08 | AA1509: 22962 | AB1509: F1 | AC1509: 1
A1510: 46273 | B1510: 46273 | C1510: CM | D1510: NSE | E1510: STK | F1510: 7128 | G1510: INE560A01023 | H1510: INDIAGLYCO | I1510: BE | N1510: INDIA GLYCOLS LTD | O1510: 274.7 | P1510: 287 | Q1510: 274.7 | R1510: 287 | S1510: 287 | T1510: 273.4 | V1510: 293.16 | Y1510: 168877 | Z1510: 48003021 | AA1510: 1428 | AB1510: F1 | AC1510: 1
A1511: 46273 | B1511: 46273 | C1511: CM | D1511: NSE | E1511: STK | F1511: 4747 | G1511: INE092B01025 | H1511: INDNIPPON | I1511: EQ | N1511: INDIA NIPPON ELECT LTD | O1511: 1130.1 | P1511: 1135.9 | Q1511: 1092 | R1511: 1122.3 | S1511: 1125 | T1511: 1128.4 | V1511: 1122.36 | Y1511: 41478 | Z1511: 46019205 | AA1511: 3970 | AB1511: F1 | AC1511: 1 | AI1511: 46044 | AJ1511: CM | AK1511: NSE | AL1511: STK | AM1511: 14518 | AN1511: INF209KB18T9 | AO1511: ABSLLIQUID | AP1511: EQ | AU1511: BIRLASLAMC - ABSLLIQUID | AV1511: 999.99 | AW1511: 1000.01 | AX1511: 999.99 | AY1511: 999.99 | AZ1511: 999.99 | BA1511: 999.99 | BC1511: 999.99 | BF1511: 1095 | BG1511: 1094990.7 | BH1511: 15 | BI1511: F1 | BJ1511: 1
A1512: 46273 | B1512: 46273 | C1512: CM | D1512: NSE | E1512: STK | F1512: 4934 | G1512: INE0D6701023 | H1512: IPL | I1512: EQ | N1512: INDIA PESTICIDES LIMITED | O1512: 136.7 | P1512: 136.79 | Q1512: 133.9 | R1512: 134.65 | S1512: 135.8 | T1512: 136.63 | V1512: 134.64 | Y1512: 129674 | Z1512: 17488802 | AA1512: 1881 | AB1512: F1 | AC1512: 1
A1513: 46273 | B1513: 46273 | C1513: CM | D1513: NSE | E1513: STK | F1513: 20556 | G1513: INE922K01024 | H1513: INDIASHLTR | I1513: EQ | N1513: INDIA SHELTER FIN CORP L | O1513: 670 | P1513: 675 | Q1513: 667.5 | R1513: 671.7 | S1513: 672.9 | T1513: 672.15 | V1513: 671.7 | Y1513: 31956 | Z1513: 21439595 | AA1513: 3428 | AB1513: F1 | AC1513: 1
A1514: 46273 | B1514: 46273 | C1514: CM | D1514: NSE | E1514: STK | F1514: 19299 | G1514: INE353K01014 | H1514: ITDC | I1514: EQ | N1514: INDIA TOUR. DEV. CO. LTD. | O1514: 643.35 | P1514: 651 | Q1514: 635.1 | R1514: 638.2 | S1514: 643.9 | T1514: 643.35 | V1514: 638.21 | Y1514: 30593 | Z1514: 19540080 | AA1514: 1760 | AB1514: F1 | AC1514: 1
A1515: 46273 | B1515: 46273 | C1515: CM | D1515: NSE | E1515: STK | F1515: 24999 | G1515: INE126M01010 | H1515: IBULLSLTD | I1515: EQ | N1515: INDIABULLS LIMITED | O1515: 25.51 | P1515: 26.39 | Q1515: 25.23 | R1515: 25.95 | S1515: 25.86 | T1515: 25.7 | V1515: 25.95 | Y1515: 15254328 | Z1515: 3.9633652e+08 | AA1515: 15259 | AB1515: F1 | AC1515: 1
A1516: 46273 | B1516: 46273 | C1516: CM | D1516: NSE | E1516: STK | F1516: 10726 | G1516: INE933S01016 | H1516: INDIAMART | I1516: EQ | N1516: INDIAMART INTERMESH LTD | O1516: 1700.1 | P1516: 1714.1 | Q1516: 1681 | R1516: 1684.5 | S1516: 1686.7 | T1516: 1706.4 | V1516: 1684.38 | Y1516: 122055 | Z1516: 2.0589688e+08 | AA1516: 11933 | AB1516: F1 | AC1516: 1
A1517: 46273 | B1517: 46273 | C1517: CM | D1517: NSE | E1517: STK | F1517: 14309 | G1517: INE562A01011 | H1517: INDIANB | I1517: EQ | N1517: INDIAN BANK | O1517: 868.5 | P1517: 868.9 | Q1517: 855.15 | R1517: 859.9 | S1517: 859.9 | T1517: 869.4 | V1517: 859.9 | Y1517: 1120827 | Z1517: 9.6446692e+08 | AA1517: 27491 | AB1517: F1 | AC1517: 1
A1518: 46273 | B1518: 46273 | C1518: CM | D1518: NSE | E1518: STK | F1518: 4422 | G1518: INE061A01014 | H1518: INDIANCARD | I1518: EQ | N1518: INDIAN CARD CLOTHING CO. | O1518: 224.4 | P1518: 224.99 | Q1518: 212.19 | R1518: 218.81 | S1518: 218.54 | T1518: 217.85 | V1518: 218.81 | Y1518: 538 | Z1518: 118346.49 | AA1518: 23 | AB1518: F1 | AC1518: 1
A1519: 46273 | B1519: 46273 | C1519: CM | D1519: NSE | E1519: STK | F1519: 23792 | G1519: INE0RRU01016 | H1519: IEML | I1519: ST | N1519: INDIAN EMULSIFIERS LTD | O1519: 41 | P1519: 43.3 | Q1519: 40.8 | R1519: 41.95 | S1519: 41.9 | T1519: 41.25 | V1519: 41.95 | Y1519: 37000 | Z1519: 1581450 | AA1519: 61 | AB1519: F1 | AC1519: 500
A1520: 46273 | B1520: 46273 | C1520: CM | D1520: NSE | E1520: STK | F1520: 220 | G1520: INE022Q01020 | H1520: IEX | I1520: EQ | N1520: INDIAN ENERGY EXC LTD | O1520: 117.5 | P1520: 117.75 | Q1520: 116 | R1520: 116.54 | S1520: 116.54 | T1520: 117.5 | V1520: 116.54 | Y1520: 4316644 | Z1520: 5.0364025e+08 | AA1520: 34642 | AB1520: F1 | AC1520: 1
A1521: 46273 | B1521: 46273 | C1521: CM | D1521: NSE | E1521: STK | F1521: 1530 | G1521: INE323C01030 | H1521: INDIANHUME | I1521: EQ | N1521: INDIAN HUME PIPE CO. LTD. | O1521: 393.6 | P1521: 395 | Q1521: 385.6 | R1521: 388.9 | S1521: 390 | T1521: 394.9 | V1521: 388.86 | Y1521: 33597 | Z1521: 13083562 | AA1521: 1435 | AB1521: F1 | AC1521: 1 | AI1521: 46044 | AJ1521: CM | AK1521: NSE | AL1521: STK | AM1521: 6297 | AN1521: INF209KB10C2 | AO1521: HEALTHY | AP1521: EQ | AU1521: BIRLASLAMC - HEALTHY | AV1521: 14.36 | AW1521: 14.6 | AX1521: 14.32 | AY1521: 14.45 | AZ1521: 14.54 | BA1521: 14.36 | BC1521: 14.45 | BF1521: 181735 | BG1521: 2623792.1 | BH1521: 1050 | BI1521: F1 | BJ1521: 1
A1522: 46273 | B1522: 46273 | C1522: CM | D1522: NSE | E1522: STK | F1522: 19235 | G1522: INE919H01018 | H1522: IMFA | I1522: EQ | N1522: INDIAN METALS & FERRO | O1522: 1287 | P1522: 1315 | Q1522: 1283.1 | R1522: 1306.7 | S1522: 1309 | T1522: 1286.9 | V1522: 1306.71 | Y1522: 74407 | Z1522: 96408641 | AA1522: 7209 | AB1522: F1 | AC1522: 1
A1523: 46273 | B1523: 46273 | C1523: CM | D1523: NSE | E1523: STK | F1523: 1624 | G1523: INE242A01010 | H1523: IOC | I1523: EQ | N1523: INDIAN OIL CORP LTD | O1523: 134.88 | P1523: 135.65 | Q1523: 133.02 | R1523: 134.35 | S1523: 134.35 | T1523: 135.15 | V1523: 134.35 | Y1523: 6954986 | Z1523: 9.3393947e+08 | AA1523: 50405 | AB1523: F1 | AC1523: 1
A1524: 46273 | B1524: 46273 | C1524: CM | D1524: NSE | E1524: STK | F1524: 9348 | G1524: INE565A01014 | H1524: IOB | I1524: EQ | N1524: INDIAN OVERSEAS BANK | O1524: 33.1 | P1524: 33.45 | Q1524: 32.9 | R1524: 33.34 | S1524: 33.4 | T1524: 33.1 | V1524: 33.34 | Y1524: 1397088 | Z1524: 46405648 | AA1524: 8215 | AB1524: F1 | AC1524: 1 | AI1524: 46044 | AJ1524: CM | AK1524: NSE | AL1524: STK | AM1524: 23590 | AN1524: INE350Z01018 | AO1524: GLOSTERLTD | AP1524: EQ | AU1524: GLOSTER LIMITED | AV1524: 584.6 | AW1524: 595 | AX1524: 584.6 | AY1524: 594.1 | AZ1524: 595 | BA1524: 584.1 | BC1524: 594.1 | BF1524: 355 | BG1524: 209584.25 | BH1524: 85 | BI1524: F1 | BJ1524: 1
A1525: 46273 | B1525: 46273 | C1525: CM | D1525: NSE | E1525: STK | F1525: 25033 | G1525: INE0DHF01018 | H1525: IPHL | I1525: SM | N1525: INDIAN PHOSPHATE LIMITED | O1525: 76.85 | P1525: 78.55 | Q1525: 76.65 | R1525: 77.05 | S1525: 77.05 | T1525: 76.1 | V1525: 77.05 | Y1525: 20400 | Z1525: 1578240 | AA1525: 16 | AB1525: F1 | AC1525: 1200
A1526: 46273 | B1526: 46273 | C1526: CM | D1526: NSE | E1526: STK | F1526: 13611 | G1526: INE335Y01020 | H1526: IRCTC | I1526: EQ | N1526: INDIAN RAIL TOUR CORP LTD | O1526: 474.5 | P1526: 474.9 | Q1526: 472 | R1526: 472.45 | S1526: 472.4 | T1526: 474.5 | V1526: 472.45 | Y1526: 412334 | Z1526: 1.9490574e+08 | AA1526: 19859 | AB1526: F1 | AC1526: 1
A1527: 46273 | B1527: 46273 | C1527: CM | D1527: NSE | E1527: STK | F1527: 2029 | G1527: INE053F01010 | H1527: IRFC | I1527: EQ | N1527: INDIAN RAILWAY FIN CORP L | O1527: 82.9 | P1527: 82.93 | Q1527: 81.75 | R1527: 82 | S1527: 82 | T1527: 83 | V1527: 82 | Y1527: 5883007 | Z1527: 4.8366175e+08 | AA1527: 39595 | AB1527: F1 | AC1527: 1
A1528: 46273 | B1528: 46273 | C1528: CM | D1528: NSE | E1528: STK | F1528: 20261 | G1528: INE202E01016 | H1528: IREDA | I1528: EQ | N1528: INDIAN RENEWABLE ENERGY | O1528: 112.5 | P1528: 112.95 | Q1528: 111.8 | R1528: 112.2 | S1528: 112.2 | T1528: 112.95 | V1528: 112.21 | Y1528: 3095995 | Z1528: 3.4728992e+08 | AA1528: 24401 | AB1528: F1 | AC1528: 1
A1529: 46273 | B1529: 46273 | C1529: CM | D1529: NSE | E1529: STK | F1529: 762727 | G1529: INE586E01020 | H1529: IWP | I1529: EQ | N1529: INDIAN WOOD PRODUCTS CO L | O1529: 35.27 | P1529: 35.27 | Q1529: 34.46 | R1529: 34.7 | S1529: 34.7 | T1529: 34.41 | V1529: 34.61 | Y1529: 3329 | Z1529: 115901.84 | AA1529: 58 | AB1529: F1 | AC1529: 1
A1530: 46273 | B1530: 46273 | C1530: CM | D1530: NSE | E1530: STK | F1530: 2048 | G1530: INE09VQ01012 | H1530: INDIGOPNTS | I1530: EQ | N1530: INDIGO PAINTS LIMITED | O1530: 1172 | P1530: 1176.2 | Q1530: 1131 | R1530: 1140.3 | S1530: 1139 | T1530: 1178 | V1530: 1140.15 | Y1530: 52024 | Z1530: 59658002 | AA1530: 6609 | AB1530: F1 | AC1530: 1
A1531: 46273 | B1531: 46273 | C1531: CM | D1531: NSE | E1531: STK | F1531: 20988 | G1531: INE219X23014 | H1531: INDIGRID | I1531: IV | N1531: INDIGRID INFRASTRUCT TRST | O1531: 175.4 | P1531: 175.4 | Q1531: 174.2 | R1531: 174.44 | S1531: 174.41 | T1531: 175.39 | V1531: 174.44 | Y1531: 436306 | Z1531: 76272981 | AA1531: 12627 | AB1531: F1 | AC1531: 1
A1532: 46273 | B1532: 46273 | C1532: CM | D1532: NSE | E1532: STK | F1532: 757845 | G1532: INE06ST01018 | H1532: INDIQUBE | I1532: EQ | N1532: INDIQUBE SPACES LIMITED | O1532: 203.61 | P1532: 206.85 | Q1532: 198.02 | R1532: 205.09 | S1532: 206.18 | T1532: 202.13 | V1532: 205.02 | Y1532: 59639 | Z1532: 12117002 | AA1532: 1334 | AB1532: F1 | AC1532: 1
A1533: 46273 | B1533: 46273 | C1533: CM | D1533: NSE | E1533: STK | F1533: 9120 | G1533: INE760F01028 | H1533: INDOAMIN | I1533: BE | N1533: INDO AMINES LIMITED | O1533: 128.4 | P1533: 128.4 | Q1533: 125.5 | R1533: 127.06 | S1533: 127.9 | T1533: 127.23 | V1533: 127.02 | Y1533: 62530 | Z1533: 7938242.2 | AA1533: 279 | AB1533: F1 | AC1533: 1
A1534: 46273 | B1534: 46273 | C1534: CM | D1534: NSE | E1534: STK | F1534: 8614 | G1534: INE803D01021 | H1534: INDOBORAX | I1534: EQ | N1534: INDO BORAX & CHEMICAL LTD | O1534: 503.3 | P1534: 515.45 | Q1534: 503.1 | R1534: 511.05 | S1534: 511 | T1534: 503.95 | V1534: 511.05 | Y1534: 95162 | Z1534: 48526673 | AA1534: 4261 | AB1534: F1 | AC1534: 1
A1535: 46273 | B1535: 46273 | C1535: CM | D1535: NSE | E1535: STK | F1535: 11987 | G1535: INE483B01026 | H1535: ICIL | I1535: EQ | N1535: INDO COUNT INDUSTRIES LTD | O1535: 451.75 | P1535: 453.45 | Q1535: 437.95 | R1535: 450.85 | S1535: 448.95 | T1535: 453.7 | V1535: 450.89 | Y1535: 292038 | Z1535: 1.3033442e+08 | AA1535: 13318 | AB1535: F1 | AC1535: 1
A1536: 46273 | B1536: 46273 | C1536: CM | D1536: NSE | E1536: STK | F1536: 29025 | G1536: INE622H01018 | H1536: INDOFARM | I1536: EQ | N1536: INDO FARM EQUIPMENT LTD | O1536: 141 | P1536: 150.19 | Q1536: 138.92 | R1536: 144.16 | S1536: 143.8 | T1536: 131.65 | V1536: 144.16 | Y1536: 2435816 | Z1536: 3.534483e+08 | AA1536: 27291 | AB1536: F1 | AC1536: 1
A1537: 46273 | B1537: 46273 | C1537: CM | D1537: NSE | E1537: STK | F1537: 10993 | G1537: INE156A01020 | H1537: INDORAMA | I1537: EQ | N1537: INDO RAMA SYNTHETICS LTD | O1537: 74.25 | P1537: 76 | Q1537: 70.72 | R1537: 74.98 | S1537: 75.36 | T1537: 73.56 | V1537: 74.98 | Y1537: 1050466 | Z1537: 76860871 | AA1537: 9995 | AB1537: F1 | AC1537: 1
A1538: 46273 | B1538: 46273 | C1538: CM | D1538: NSE | E1538: STK | F1538: 13275 | G1538: INE332H01014 | H1538: INDOTECH | I1538: EQ | N1538: INDO TECH TRANSFORM LTD. | O1538: 3679.9 | P1538: 3848.9 | Q1538: 3600 | R1538: 3696.8 | S1538: 3699.7 | T1538: 3666.6 | V1538: 3695.96 | Y1538: 26581 | Z1538: 98853238 | AA1538: 3836 | AB1538: F1 | AC1538: 1 | AI1538: 46044 | AJ1538: CM | AK1538: NSE | AL1538: STK | AM1538: 6994 | AN1538: INE836A01035 | AO1538: BSOFT | AP1538: EQ | AU1538: BIRLASOFT LIMITED | AV1538: 411 | AW1538: 418 | AX1538: 410.95 | AY1538: 415.4 | AZ1538: 414.4 | BA1538: 407.25 | BC1538: 415.4 | BF1538: 488647 | BG1538: 2.0275073e+08 | BH1538: 17436 | BI1538: F1 | BJ1538: 1
A1539: 46273 | B1539: 46273 | C1539: CM | D1539: NSE | E1539: STK | F1539: 25608 | G1539: INE337M01021 | H1539: INDOTHAI | I1539: EQ | N1539: INDO THAI SEC LTD | O1539: 39.4 | P1539: 39.4 | Q1539: 39.4 | R1539: 39.4 | S1539: 39.4 | T1539: 37.53 | V1539: 39.44 | Y1539: 59211 | Z1539: 2332913.4 | AA1539: 103 | AB1539: F1 | AC1539: 1
A1540: 46273 | B1540: 46273 | C1540: CM | D1540: NSE | E1540: STK | F1540: 25503 | G1540: INE250Z01010 | H1540: INDOUS | I1540: EQ | N1540: INDO US BIOTECH LTD | O1540: 78.81 | P1540: 83 | Q1540: 78.05 | R1540: 78.85 | S1540: 80.33 | T1540: 78.74 | V1540: 78.85 | Y1540: 13629 | Z1540: 1082557.2 | AA1540: 193 | AB1540: F1 | AC1540: 1
A1541: 46273 | B1541: 46273 | C1541: CM | D1541: NSE | E1541: STK | F1541: 764301 | G1541: INE084101034 | H1541: INDOMIM | I1541: EQ | N1541: INDO-MIM LIMITED | O1541: 951 | P1541: 989 | Q1541: 943.75 | R1541: 968.95 | S1541: 967 | T1541: 946.7 | V1541: 968.9 | Y1541: 2185054 | Z1541: 2.1193678e+09 | AA1541: 72778 | AB1541: F1 | AC1541: 1
A1542: 46273 | B1542: 46273 | C1542: CM | D1542: NSE | E1542: STK | F1542: 6782 | G1542: INE567A01028 | H1542: NIPPOBATRY | I1542: EQ | N1542: INDO-NATIONAL LIMITED | O1542: 321.2 | P1542: 329.9 | Q1542: 320 | R1542: 324.6 | S1542: 324.85 | T1542: 325.25 | V1542: 324.6 | Y1542: 2175 | Z1542: 705237.05 | AA1542: 519 | AB1542: F1 | AC1542: 1
A1543: 46273 | B1543: 46273 | C1543: CM | D1543: NSE | E1543: STK | F1543: 11677 | G1543: INE873D01024 | H1543: INDOCO | I1543: EQ | N1543: INDOCO REMEDIES LTD. | O1543: 250.73 | P1543: 256.88 | Q1543: 243 | R1543: 244.25 | S1543: 244 | T1543: 250.7 | V1543: 244.25 | Y1543: 176170 | Z1543: 43345034 | AA1543: 4243 | AB1543: F1 | AC1543: 1
A1544: 46273 | B1544: 46273 | C1544: CM | D1544: NSE | E1544: STK | F1544: 757801 | G1544: INE05J901018 | H1544: IGCL | I1544: EQ | N1544: INDOGULF CROPSCIENCES LTD | O1544: 73.47 | P1544: 73.47 | Q1544: 72.1 | R1544: 72.54 | S1544: 72.2 | T1544: 72.48 | V1544: 72.53 | Y1544: 177043 | Z1544: 12854822 | AA1544: 1418 | AB1544: F1 | AC1544: 1
A1545: 46273 | B1545: 46273 | C1545: CM | D1545: NSE | E1545: STK | F1545: 764708 | G1545: INE716F01012 | H1545: INDOKEM | I1545: EQ | N1545: INDOKEM LTD. | O1545: 649.85 | P1545: 649.85 | Q1545: 624.9 | R1545: 627.4 | S1545: 630 | T1545: 636.35 | V1545: 626.81 | Y1545: 2468 | Z1545: 1562802.6 | AA1545: 179 | AB1545: F1 | AC1545: 1
A1546: 46273 | B1546: 46273 | C1546: CM | D1546: NSE | E1546: STK | F1546: 19955 | G1546: INE866K01023 | H1546: WAAREEINDO | I1546: EQ | N1546: INDOSOLAR LIMITED | O1546: 267.4 | P1546: 267.4 | Q1546: 261.2 | R1546: 262.05 | S1546: 262 | T1546: 265.55 | V1546: 262.05 | Y1546: 52149 | Z1546: 13762564 | AA1546: 1266 | AB1546: F1 | AC1546: 1 | AI1546: 46044 | AJ1546: CM | AK1546: NSE | AL1546: STK | AM1546: 144 | AN1546: INE850D01014 | AO1546: GODREJAGRO | AP1546: EQ | AU1546: GODREJ AGROVET LIMITED | AV1546: 525.65 | AW1546: 527 | AX1546: 517.15 | AY1546: 524.45 | AZ1546: 525.85 | BA1546: 517.9 | BC1546: 524.45 | BF1546: 70773 | BG1546: 36909536 | BH1546: 6531 | BI1546: F1 | BJ1546: 1
A1547: 46273 | B1547: 46273 | C1547: CM | D1547: NSE | E1547: STK | F1547: 3088 | G1547: INE896L01010 | H1547: INDOSTAR | I1547: EQ | N1547: INDOSTAR CAPITAL FIN LTD | O1547: 253.95 | P1547: 254.55 | Q1547: 250 | R1547: 251.29 | S1547: 250 | T1547: 253.08 | V1547: 251.14 | Y1547: 35032 | Z1547: 8830674.9 | AA1547: 696 | AB1547: F1 | AC1547: 1
A1548: 46273 | B1548: 46273 | C1548: CM | D1548: NSE | E1548: STK | F1548: 14952 | G1548: INE227G01018 | H1548: INDOWIND | I1548: EQ | N1548: INDOWIND ENERGY LTD | O1548: 9.09 | P1548: 9.1 | Q1548: 8.65 | R1548: 8.85 | S1548: 8.94 | T1548: 8.91 | V1548: 8.85 | Y1548: 112368 | Z1548: 1001053.6 | AA1548: 460 | AB1548: F1 | AC1548: 1
A1549: 46273 | B1549: 46273 | C1549: CM | D1549: NSE | E1549: STK | F1549: 11262 | G1549: INE203G01027 | H1549: IGL | I1549: EQ | N1549: INDRAPRASTHA GAS LTD | O1549: 153.25 | P1549: 154.49 | Q1549: 152.7 | R1549: 154.02 | S1549: 153.7 | T1549: 154.8 | V1549: 154.02 | Y1549: 834619 | Z1549: 1.2820254e+08 | AA1549: 11356 | AB1549: F1 | AC1549: 1
A1550: 46273 | B1550: 46273 | C1550: CM | D1550: NSE | E1550: STK | F1550: 4751 | G1550: INE681B01017 | H1550: INDRAMEDCO | I1550: EQ | N1550: INDRAPRASTHA MEDICAL CORP | O1550: 351.95 | P1550: 356.2 | Q1550: 348.45 | R1550: 355.15 | S1550: 355.25 | T1550: 351.4 | V1550: 355.12 | Y1550: 126540 | Z1550: 44572359 | AA1550: 4019 | AB1550: F1 | AC1550: 1
A1551: 46273 | B1551: 46273 | C1551: CM | D1551: NSE | E1551: STK | F1551: 23036 | G1551: INE0NHL23019 | H1551: INDUSINVIT | I1551: IV | N1551: INDUS INFRA TRUST | O1551: 133.58 | P1551: 134 | Q1551: 132.81 | R1551: 132.98 | S1551: 132.82 | T1551: 132.97 | V1551: 132.98 | Y1551: 127304 | Z1551: 16945969 | AA1551: 5297 | AB1551: F1 | AC1551: 1
A1552: 46273 | B1552: 46273 | C1552: CM | D1552: NSE | E1552: STK | F1552: 29135 | G1552: INE121J01017 | H1552: INDUSTOWER | I1552: EQ | N1552: INDUS TOWERS LIMITED | O1552: 376.45 | P1552: 376.95 | Q1552: 370 | R1552: 373.05 | S1552: 373.05 | T1552: 376.45 | V1552: 373.05 | Y1552: 2490099 | Z1552: 9.2740639e+08 | AA1552: 48179 | AB1552: F1 | AC1552: 1
A1553: 46273 | B1553: 46273 | C1553: CM | D1553: NSE | E1553: STK | F1553: 5258 | G1553: INE095A01012 | H1553: INDUSINDBK | I1553: EQ | N1553: INDUSIND BANK LIMITED | O1553: 991.6 | P1553: 1004.7 | Q1553: 988.3 | R1553: 997.7 | S1553: 997.7 | T1553: 998 | V1553: 997.71 | Y1553: 1055105 | Z1553: 1.0520145e+09 | AA1553: 35795 | AB1553: F1 | AC1553: 1
A1554: 46273 | B1554: 46273 | C1554: CM | D1554: NSE | E1554: STK | F1554: 762717 | G1554: INE620D01011 | H1554: INDPRUD | I1554: EQ | N1554: INDUSTRIAL & PRU INV CO L | O1554: 6389 | P1554: 6389 | Q1554: 6200 | R1554: 6210 | S1554: 6210 | T1554: 6385 | V1554: 6185 | Y1554: 119 | Z1554: 746998.5 | AA1554: 23 | AB1554: F1 | AC1554: 1
A1555: 46273 | B1555: 46273 | C1555: CM | D1555: NSE | E1555: STK | F1555: 19525 | G1555: INE886A01014 | H1555: IITL | I1555: EQ | N1555: INDUSTRIAL INV TRUST LTD | O1555: 141.01 | P1555: 159.15 | Q1555: 139.08 | R1555: 149.88 | S1555: 149.25 | T1555: 140.1 | V1555: 149.87 | Y1555: 155404 | Z1555: 22986051 | AA1555: 3850 | AB1555: F1 | AC1555: 1
A1556: 46273 | B1556: 46273 | C1556: CM | D1556: NSE | E1556: STK | F1556: 15036 | G1556: INE0MRE01011 | H1556: INFINIUM | I1556: SM | N1556: INFINIUM PHARMACHEM LTD | O1556: 274 | P1556: 277.5 | Q1556: 270.2 | R1556: 277.45 | S1556: 277.45 | T1556: 274.9 | V1556: 277.45 | Y1556: 6500 | Z1556: 1792150 | AA1556: 11 | AB1556: F1 | AC1556: 500
A1557: 46273 | B1557: 46273 | C1557: CM | D1557: NSE | E1557: STK | F1557: 757602 | G1557: INE0MYZ01012 | H1557: INFLUX | I1557: SM | N1557: INFLUX HEALTHTECH LIMITED | O1557: 285 | P1557: 287.95 | Q1557: 282 | R1557: 283.7 | S1557: 282 | T1557: 288.6 | V1557: 283.7 | Y1557: 13200 | Z1557: 3749880 | AA1557: 22 | AB1557: F1 | AC1557: 600 | AI1557: 46044 | AJ1557: CM | AK1557: NSE | AL1557: STK | AM1557: 27273 | AN1557: IN0020240159 | AO1557: 679GS2034A | AP1557: GS | AU1557: GOI LOAN 6.79% 2034 | AV1557: 99.64 | AW1557: 99.64 | AX1557: 97.65 | AY1557: 97.65 | AZ1557: 97.65 | BA1557: 99.64 | BC1557: 97.65 | BF1557: 200 | BG1557: 19729 | BH1557: 2 | BI1557: F1 | BJ1557: 1
A1558: 46273 | B1558: 46273 | C1558: CM | D1558: NSE | E1558: STK | F1558: 13751 | G1558: INE663F01032 | H1558: NAUKRI | I1558: EQ | N1558: INFO EDGE (I) LTD | O1558: 1274.5 | P1558: 1298.3 | Q1558: 1251.9 | R1558: 1292 | S1558: 1292 | T1558: 1302.5 | V1558: 1292.03 | Y1558: 2345489 | Z1558: 3015527062 | AA1558: 71658 | AB1558: F1 | AC1558: 1
A1559: 46273 | B1559: 46273 | C1559: CM | D1559: NSE | E1559: STK | F1559: 11027 | G1559: INE344S01016 | H1559: INFOBEAN | I1559: EQ | N1559: INFOBEANS TECHNO. LTD. | O1559: 159.2 | P1559: 160.13 | Q1559: 157.1 | R1559: 158.61 | S1559: 157.6 | T1559: 159.73 | V1559: 158.64 | Y1559: 202682 | Z1559: 32075421 | AA1559: 3207 | AB1559: F1 | AC1559: 1
A1560: 46273 | B1560: 46273 | C1560: CM | D1560: NSE | E1560: STK | F1560: 16588 | G1560: INE0NNZ01013 | H1560: INFOLLION | I1560: SM | N1560: INFOLLION RESEARCH SER L | O1560: 156 | P1560: 157 | Q1560: 151.15 | R1560: 154 | S1560: 153.05 | T1560: 155.65 | V1560: 154 | Y1560: 23600 | Z1560: 3676340 | AA1560: 43 | AB1560: F1 | AC1560: 400
A1561: 46273 | B1561: 46273 | C1561: CM | D1561: NSE | E1561: STK | F1561: 13693 | G1561: INE669A01022 | H1561: INFOMEDIA | I1561: EQ | N1561: INFOMEDIA PRESS LIMITED | O1561: 5.21 | P1561: 5.8 | Q1561: 5.21 | R1561: 5.53 | S1561: 5.42 | T1561: 5.43 | V1561: 5.53 | Y1561: 36530 | Z1561: 202307.69 | AA1561: 131 | AB1561: F1 | AC1561: 1
A1562: 46273 | B1562: 46273 | C1562: CM | D1562: NSE | E1562: STK | F1562: 1594 | G1562: INE009A01021 | H1562: INFY | I1562: EQ | N1562: INFOSYS LIMITED | O1562: 1095 | P1562: 1095 | Q1562: 1078.9 | R1562: 1082 | S1562: 1082 | T1562: 1087.5 | V1562: 1082 | Y1562: 6269037 | Z1562: 6.7974339e+09 | AA1562: 151673 | AB1562: F1 | AC1562: 1
A1563: 46273 | B1563: 46273 | C1563: CM | D1563: NSE | E1563: STK | F1563: 1597 | G1563: INE177A01018 | H1563: INGERRAND | I1563: EQ | N1563: INGERSOLL-RAND INDIA LTD | O1563: 4754 | P1563: 4769.9 | Q1563: 4692.3 | R1563: 4741.7 | S1563: 4760 | T1563: 4730.3 | V1563: 4741.77 | Y1563: 10123 | Z1563: 47801303 | AA1563: 2117 | AB1563: F1 | AC1563: 1 | AI1563: 46044 | AJ1563: CM | AK1563: NSE | AL1563: STK | AM1563: 3202 | AN1563: IN0020210012 | AO1563: 563GS2026 | AP1563: GS | AU1563: GOI LOAN 5.63% 2026 | AV1563: 101.6 | AW1563: 101.6 | AX1563: 101.33 | AY1563: 101.33 | AZ1563: 101.33 | BA1563: 101.35 | BC1563: 101.35 | BF1563: 22 | BG1563: 2233.58 | BH1563: 5 | BI1563: F1 | BJ1563: 1
A1564: 46273 | B1564: 46273 | C1564: CM | D1564: NSE | E1564: STK | F1564: 25323 | G1564: INE0S1D01010 | H1564: INNOMET | I1564: ST | N1564: INNOMET ADVANCED MATERI L | O1564: 282.3 | P1564: 293.75 | Q1564: 282.3 | R1564: 288.9 | S1564: 288.9 | T1564: 288.05 | V1564: 288.9 | Y1564: 133200 | Z1564: 38126850 | AA1564: 140 | AB1564: F1 | AC1564: 600
A1565: 46273 | B1565: 46273 | C1565: CM | D1565: NSE | E1565: STK | F1565: 21062 | G1565: INE0DUT01020 | H1565: INNOVACAP | I1565: EQ | N1565: INNOVA CAPTAB LIMITED | O1565: 1172 | P1565: 1185.8 | Q1565: 1164 | R1565: 1171.8 | S1565: 1180 | T1565: 1164.4 | V1565: 1171.84 | Y1565: 34248 | Z1565: 40127902 | AA1565: 5399 | AB1565: F1 | AC1565: 1
A1566: 46273 | B1566: 46273 | C1566: CM | D1566: NSE | E1566: STK | F1566: 27754 | G1566: INE403Y01018 | H1566: INNOVANA | I1566: EQ | N1566: INNOVANA THINKLABS LTD | O1566: 300.6 | P1566: 314.4 | Q1566: 300.1 | R1566: 300.55 | S1566: 300.1 | T1566: 301.65 | V1566: 300.83 | Y1566: 32871 | Z1566: 10103259 | AA1566: 294 | AB1566: F1 | AC1566: 1
A1567: 46273 | B1567: 46273 | C1567: CM | D1567: NSE | E1567: STK | F1567: 27266 | G1567: INE070Y01023 | H1567: ITTL | I1567: ST | N1567: INNOVATIVE TYRE & TUBE LT | O1567: 65.45 | P1567: 65.45 | Q1567: 65.45 | R1567: 65.45 | S1567: 65.45 | T1567: 65.45 | V1567: 65.45 | Y1567: 105 | Z1567: 6872.25 | AA1567: 1 | AB1567: F1 | AC1567: 105
A1568: 46273 | B1568: 46273 | C1568: CM | D1568: NSE | E1568: STK | F1568: 761528 | G1568: INE0ADB01012 | H1568: INNOVISION | I1568: EQ | N1568: INNOVISION LIMITED | O1568: 254.15 | P1568: 258.9 | Q1568: 250.75 | R1568: 252 | S1568: 252.75 | T1568: 256.25 | V1568: 251.98 | Y1568: 8849 | Z1568: 2234751 | AA1568: 730 | AB1568: F1 | AC1568: 1 | AI1568: 46044 | AJ1568: CM | AK1568: NSE | AL1568: STK | AM1568: 757753 | AN1568: IN0020250034 | AO1568: 591GS2028 | AP1568: GS | AU1568: GOI LOAN 5.91% 2028 | AV1568: 99.18 | AW1568: 99.18 | AX1568: 99.18 | AY1568: 99.18 | AZ1568: 99.18 | BA1568: 99.13 | BC1568: 99.18 | BF1568: 100 | BG1568: 9918 | BH1568: 1 | BI1568: F1 | BJ1568: 1
...

Sheet Stocks
A1: SYMBOL | B1: Stocks | E1: Quantity | F1: Value
A3: ASHAPURMIN | B3: ASHAPURMIN | C3: =VLOOKUP(A3,cmbhavcopy!H:R,11,0) -> 549.35 | E3: 499364 | F3: =E3*C3 -> 2.7432561e+08
A4: ASTRAMICRO | B4: ASTRAMICRO | C4: =VLOOKUP(A4,cmbhavcopy!H:R,11,0) -> 1757.3 | E4: 868826 | F4: =E4*C4 -> 1.5267879e+09
A5: ATHERENERG | B5: ATHERENERG | C5: =VLOOKUP(A5,cmbhavcopy!H:R,11,0) -> 1578 | E5: 310284 | F5: =E5*C5 -> 489628152
A6: AURIONPRO | B6: AURIONPRO | C6: =VLOOKUP(A6,cmbhavcopy!H:R,11,0) -> 672.1 | E6: 265374 | F6: =E6*C6 -> 1.7835787e+08
A7: AVALON | B7: AVALON | C7: =VLOOKUP(A7,cmbhavcopy!H:R,11,0) -> 2290.3 | E7: 535081 | F7: =E7*C7 -> 1.225496e+09
A8: BIRLANU | B8: BIRLANU | C8: =VLOOKUP(A8,cmbhavcopy!H:R,11,0) -> 1433.2 | E8: 93338 | F8: =E8*C8 -> 1.3377202e+08
A9: E2E | B9: E2E | C9: =VLOOKUP(A9,cmbhavcopy!H:R,11,0) -> 617.6 | E9: 1019044 | F9: =E9*C9 -> 6.2936157e+08
A10: HCG | B10: HCG | C10: =VLOOKUP(A10,cmbhavcopy!H:R,11,0) -> 690.6 | E10: 707396 | F10: =E10*C10 -> 4.8852768e+08
A11: HEG | B11: HEG | C11: =VLOOKUP(A11,cmbhavcopy!H:R,11,0) -> 258.6 | E11: 477184 | F11: =E11*C11 -> 1.2339978e+08
A12: HERITGFOOD | B12: HERITGFOOD | C12: =VLOOKUP(A12,cmbhavcopy!H:R,11,0) -> 382.15 | E12: 880487 | F12: =E12*C12 -> 3.3647811e+08
A13: HINDOILEXP | B13: HINDOILEXP | C13: =VLOOKUP(A13,cmbhavcopy!H:R,11,0) -> 193.66 | E13: 662591 | F13: =E13*C13 -> 1.2831737e+08
A14: INOXWIND | B14: INOXWIND | C14: =VLOOKUP(A14,cmbhavcopy!H:R,11,0) -> 75.71 | E14: 2030114 | F14: =E14*C14 -> 1.5369993e+08
... A20: ZENTEC | B20: ZENTEC | C20: =VLOOKUP(A20,cmbhavcopy!H:R,11,0) -> 1825 | E20: 537434 | F20: =E20*C20 -> 980817050
A21: NIFTYBEES | B21: NIFTYBEES | C21: =VLOOKUP(A21,cmbhavcopy!H:R,11,0) -> 270.05
A22: JUNIORBEES | B22: JUNIORBEES | C22: =VLOOKUP(A22,cmbhavcopy!H:R,11,0) -> 787.59
A23: LIQUIDCASE | B23: LIQUIDCASE | C23: =VLOOKUP(A23,cmbhavcopy!H:R,11,0) -> 115.82 | E23: 2156007 | F23: =E23*C23 -> 2.4970873e+08
A24: SENSEX | B24: SENSEX | C24: 76957.27
A25: BSEMIDCAP | B25: BSEMIDCAP | C25: 49203.59
A26: BSESMALLCAP | B26: BSESMALLCAP | C26: 58865
A27: BSE500 | B27: BSE500 | C27: 36615.95

Sheet Model
A1: Model | B1: Qnty | C1: Price | D1: Value | E1: Percent | F1: Index | G1: Mcap | H1: Date | I1: %Firm | J1: Value | K1: Portfolio | L1: 2012 | M1: 1000000 | N1: 1847556.4 | O1: =(N1-M1)/M1 -> 0.84755644 | Q1: BSESmallCap | R1: 2012 | S1: 5550.14 | T1: 7379.94 | U1: =(T1-S1)/S1 -> 0.32968538
L2: 2013 | M2: 1847556.4 | N2: 2235154.8 | O2: =(N2-M2)/M2 -> 0.2097897 | P2: =(N2-M1)/M1 -> 1.2351547 | R2: 2013 | S2: 7379.94 | T2: 6551.13 | U2: =(T2-S2)/S2 -> -0.11230579 | V2: =(T2-S1)/S1 -> 0.18035401
A3: ASHAPURMIN | B3: 3670 | C3: =Stocks!C3 -> 549.35 | D3: =B3*C3 -> 2016114.5 | E3: =D3/$D$24*100 -> 2.8695928 | F3: - | G3: =(19.11/2)*C3 -> 5249.0392 | H3: Nov25 | I3: =(Stocks!E3*C3)/(G3*100000) -> 0.52262062 | J3: 810 | L3: 2014 | M3: 2235154.8 | N3: 5014401.5 | O3: =(N3-M3)/M3 -> 1.2434247 | P3: =(N3-M1)/M1 -> 4.0144015 | R3: 2014 | S3: 6551.13 | T3: 11087.07 | U3: =(T3-S3)/S3 -> 0.69239047 | V3: =(T3-S1)/S1 -> 0.99761988
A4: ASTRAMICRO | B4: 6750 | C4: =Stocks!C4 -> 1757.3 | D4: =B4*C4 -> 11861775 | E4: =D4/$D$24*100 -> 16.8832 | F4: Smallcap | G4: =(18.99/2)*C4 -> 16685.563 | H4: Feb23 | I4: =(Stocks!E4*C4)/(G4*100000) -> 0.91503528 | J4: 1100 | L4: 2015 | M4: 5014401.5 | N4: 5993366 | O4: =(N4-M4)/M4 -> 0.19523059 | P4: =(N4-M1)/M1 -> 4.993366 | R4: 2015 | S4: 11087.07 | T4: 11836.71 | U4: =(T4-S4)/S4 -> 0.067613896 | V4: =(T4-S1)/S1 -> 1.1326867
A5: ATHERENERG | B5: 2300 | C5: =Stocks!C5 -> 1578 | D5: =B5*C5 -> 3629400 | E5: =D5/$D$24*100 -> 5.1658277 | F5: - | G5: =(38.26/1)*C5 -> 60374.28 | H5: Apr26 | I5: =(Stocks!E5*C5)/(G5*100000) -> 0.081098798 | J5: 1450 | L5: 2016 | M5: 5993366 | N5: 6462585.6 | O5: =(N5-M5)/M5 -> 0.078289821 | P5: =(N5-$M$1)/$M$1 -> 5.4625856 | R5: 2016 | S5: 11836.71 | T5: 12046.13 | U5: =(T5-S5)/S5 -> 0.017692416 | V5: =(T5-$S$1)/$S$1 -> 1.1704191
A6: AURIONPRO | B6: 1955 | C6: =Stocks!C6 -> 672.1 | D6: =B6*C6 -> 1313955.5 | E6: =D6/$D$24*100 -> 1.87019 | F6: Smallcap | G6: =(53.71/10)*C6 -> 3609.8491 | H6: May24 | I6: =(Stocks!E6*C6)/(G6*100000) -> 0.49408676 | J6: 790 | L6: 2017 | M6: 6462585.6 | N6: 10375693 | O6: =(N6-M6)/M6 -> 0.6055018 | P6: =(N6-$M$1)/$M$1 -> 9.3756928 | R6: 2017 | S6: 12046.13 | T6: 19230.72 | U6: =(T6-S6)/S6 -> 0.59642308 | V6: =(T6-$S$1)/$S$1 -> 2.4649072
A7: AVALON | B7: 3978 | C7: =Stocks!C7 -> 2290.3 | D7: =B7*C7 -> 9110813.4 | E7: =D7/$D$24*100 -> 12.967678 | F7: Smallcap | G7: =(13.23/2)*C7 -> 15150.335 | H7: Dec24 | I7: =(Stocks!E7*C7)/(G7*100000) -> 0.8088904 | J7: 1450 | L7: 2018 | M7: 10375693 | N7: 7842995.9 | O7: =(N7-M7)/M7 -> -0.24409906 | P7: =(N7-$M$1)/$M$1 -> 6.8429959 | R7: 2018 | S7: 19230.72 | T7: 14706.69 | U7: =(T7-S7)/S7 -> -0.23525016 | V7: =(T7-$S$1)/$S$1 -> 1.6497872
A8: BIRLANU | B8: 649 | C8: =Stocks!C8 -> 1433.2 | D8: =B8*C8 -> 930146.8 | E8: =D8/$D$24*100 -> 1.3239043 | F8: Smallcap | G8: =(7.57/10)*C8 -> 1084.9324 | H8: Jun20 | I8: =(Stocks!E8*C8)/(G8*100000) -> 1.2329987 | J8: 1850 | L8: 2019 | M8: 7842995.9 | N8: 6545182.7 | O8: =(N8-M8)/M8 -> -0.16547416 | P8: =(N8-$M$1)/$M$1 -> 5.5451827 | R8: 2019 | S8: 14706.69 | T8: 13699.37 | U8: =(T8-S8)/S8 -> -0.068493998 | V8: =(T8-$S$1)/$S$1 -> 1.4682927
A9: E2E | B9: 7556 | C9: =Stocks!C9 -> 617.6 | D9: =B9*C9 -> 4666585.6 | E9: =D9/$D$24*100 -> 6.6420833 | F9: Smallcap | G9: =(20.6/1)*C9 -> 12722.56 | H9: May25 | I9: =(Stocks!E9*C9)/(G9*100000) -> 0.49468155 | J9: 415 | L9: 2020 | M9: 6545182.7 | N9: 12616390 | O9: =(N9-M9)/M9 -> 0.92758413 | P9: =(N9-$M$1)/$M$1 -> 11.61639 | R9: 2020 | S9: 13699.37 | T9: 18098.11 | U9: =(T9-S9)/S9 -> 0.32109068 | V9: =(T9-$S$1)/$S$1 -> 2.2608385
A10: HCG | B10: 5203 | C10: =Stocks!C10 -> 690.6 | D10: =B10*C10 -> 3593191.8 | E10: =D10/$D$24*100 -> 5.1142915 | F10: Smallcap | G10: =(139.42/10)*C10 -> 9628.3452 | H10: Oct25 | I10: =(Stocks!E10*C10)/(G10*100000) -> 0.50738488 | J10: 780 | L10: 2021 | M10: 12616390 | N10: 28210591 | O10: =(N10-M10)/M10 -> 1.2360271 | P10: =(N10-$M$1)/$M$1 -> 27.210591 | R10: 2021 | S10: 18098.11 | T10: 29457.76 | U10: =(T10-S10)/S10 -> 0.62767051 | V10: =(T10-$S$1)/$S$1 -> 4.3075706
A11: HEG | B11: 4078 | C11: =Stocks!C11 -> 258.6 | D11: =B11*C11 -> 1054570.8 | E11: =D11/$D$24*100 -> 1.5010004 | F11: BSE500 | G11: =(38.59/2)*C11 -> 4989.687 | H11: Apr26 | I11: =(Stocks!E11*C11)/(G11*100000) -> 0.24730967 | J11: 720 | L11: 2022 | M11: 28210591 | N11: 23623019 | O11: =(N11-M11)/M11 -> -0.16261877 | P11: =(N11-$M$1)/$M$1 -> 22.623019 | R11: 2022 | S11: 29457.76 | T11: 28926.79 | U11: =(T11-S11)/S11 -> -0.018024792 | V11: =(T11-$S$1)/$S$1 -> 4.2119028
A12: HEGGraphite | B12: 4078 | C12: 468.25 | D12: =B12*C12 -> 1909523.5 | E12: =D12/$D$24*100 -> 2.7178788 | F12: BSE500 | G12: =(38.59/2)*C12 -> 9034.8838 | H12: Apr26 | I12: =(Stocks!E12*C12)/(G12*100000) -> 0.4563291 | L12: 2023 | M12: 23623019 | N12: 47222616 | O12: =(N12-M12)/M12 -> 0.99900848 | P12: =(N12-$M$1)/$M$1 -> 46.222616 | R12: 2023 | S12: 28926.79 | T12: 42673.76 | U12: =(T12-S12)/S12 -> 0.47523317 | V12: =(T12-$S$1)/$S$1 -> 6.6887718
A13: HERITGFOOD | B13: 6241 | C13: =Stocks!C12 -> 382.15 | D13: =B13*C13 -> 2384998.1 | E13: =D13/$D$24*100 -> 3.3946353 | F13: Smallcap | G13: =(46.12/5)*C13 -> 3524.9516 | H13: Sep12 | I13: =(Stocks!E12*C13)/(G13*100000) -> 0.95456093 | J13: 425 | L13: 2024 | M13: 47222616 | N13: 63942509 | O13: =(N13-M13)/M13 -> 0.35406538 | P13: =(N13-$M$1)/$M$1 -> 62.942509 | R13: 2024 | S13: 42673.76 | T13: 55180.6 | U13: =(T13-S13)/S13 -> 0.29308034 | V13: =(T13-$S$1)/$S$1 -> 8.9421997
A14: HINDOILEXP | B14: 4785 | C14: =Stocks!C13 -> 193.66 | D14: =B14*C14 -> 926663.1 | E14: =D14/$D$24*100 -> 1.3189458 | F14: Smallcap | G14: =(130.51/10)*C14 -> 2527.4567 | H14: Feb17 | I14: =(Stocks!E13*C14)/(G14*100000) -> 0.50769366 | J14: 150 | L14: 2025 | M14: 63942509 | N14: 53586889 | O14: =(N14-M14)/M14 -> -0.16195205 | P14: =(N14-$M$1)/$M$1 -> 52.586889 | R14: 2025 | S14: 55180.6 | T14: 51525.46 | U14: =(T14-S14)/S14 -> -0.066239584 | V14: =(T14-$S$1)/$S$1 -> 8.2836325
A15: INOXWIND | B15: 13656 | C15: =Stocks!C14 -> 75.71 | D15: =B15*C15 -> 1033895.8 | E15: =D15/$D$24*100 -> 1.4715731 | F15: BSE500 | G15: =(1728.4/10)*C15 -> 13085.716 | H15: May26 | I15: =(Stocks!E14*C15)/(G15*100000) -> 0.11745626 | J15: 100 | L15: 2026 | M15: 53586889 | N15: =D24 -> 70257860 | O15: =(N15-M15)/M15 -> 0.31110169 | P15: =(N15-$M$1)/$M$1 -> 69.25786 | R15: 2026 | S15: 51525.46 | T15: =Stocks!C26 -> 58865 | U15: =(T15-S15)/S15 -> 0.14244492 | V15: =(T15-$S$1)/$S$1 -> 9.6060388
A16: JYOTICNC | B16: 1995 | C16: =Stocks!C15 -> 1037.2 | D16: =B16*C16 -> 2069214 | E16: =D16/$D$24*100 -> 2.9451708 | F16: BSE500 | G16: =(45.19/2)*C16 -> 23435.534 | H16: Aug26 | I16: =(Stocks!E15*C16)/(G16*100000) -> 0.11837929
A17: POWERMECH | B17: 1719 | C17: =Stocks!C16 -> 2415.1 | D17: =B17*C17 -> 4151556.9 | E17: =D17/$D$24*100 -> 5.9090284 | F17: Smallcap | G17: =(31.62/10)*C17 -> 7636.5462 | H17: Sep22 | I17: =(Stocks!E16*C17)/(G17*100000) -> 0.74682796 | J17: 2580 | K17: BSEMidCap | L17: 2012 | M17: 5135.05 | N17: 7112.89 | O17: =(N17-M17)/M17 -> 0.3851647 | Q17: Sensex | R17: 2012 | S17: 15454.92 | T17: 19426.71 | U17: =(T17-S17)/S17 -> 0.25699195
A18: THOMASCOOK | B18: 27893 | C18: =Stocks!C17 -> 109.91 | D18: =B18*C18 -> 3065719.6 | E18: =D18/$D$24*100 -> 4.3635255 | F18: Smallcap | G18: =(47.04/1)*C18 -> 5170.1664 | H18: Nov23 | I18: =(Stocks!E17*C18)/(G18*100000) -> 0.83069366 | J18: 127 | L18: 2013 | M18: 7112.89 | N18: 6705.56 | O18: =(N18-M18)/M18 -> -0.057266456 | P18: =(N18-M17)/M17 -> 0.30584123 | R18: 2013 | S18: 19426.71 | T18: 21170.68 | U18: =(T18-S18)/S18 -> 0.089771763 | V18: =(T18-$S$17)/$S$17 -> 0.36983433
A19: VADILALIND | B19: 753 | C19: =Stocks!C18 -> 7534.5 | D19: =B19*C19 -> 5673478.5 | E19: =D19/$D$24*100 -> 8.0752224 | F19: Smallcap | G19: =(7.19/10)*C19 -> 5417.3055 | H19: Nov22 | I19: =(Stocks!E18*C19)/(G19*100000) -> 1.4270793 | J19: 6800 | L19: 2014 | M19: 6705.56 | N19: 10372.58 | O19: =(N19-M19)/M19 -> 0.5468626 | P19: =(N19-M17)/M17 -> 1.019957 | R19: 2014 | S19: 21170.68 | T19: 27499.42 | U19: =(T19-S19)/S19 -> 0.29893891 | V19: =(T19-$S$17)/$S$17 -> 0.77933111
A20: VRLLOG | B20: 10848 | C20: =Stocks!C19 -> 293.75 | D20: =B20*C20 -> 3186600 | E20: =D20/$D$24*100 -> 4.5355779 | F20: Smallcap | G20: =(176.68/10)*C20 -> 5189.975 | H20: Feb21 | I20: =(Stocks!E19*C20)/(G20*100000) -> 0.83590446 | J20: 380 | L20: 2015 | M20: 10372.58 | N20: 11143.08 | O20: =(N20-M20)/M20 -> 0.074282387 | P20: =(N20-$M$17)/$M$17 -> 1.1700042 | R20: 2015 | S20: 27499.42 | T20: 26117.54 | U20: =(T20-S20)/S20 -> -0.050251242 | V20: =(T20-$S$17)/$S$17 -> 0.68991751
A21: ZENTEC | B21: 3930 | C21: =Stocks!C20 -> 1825 | D21: =B21*C21 -> 7172250 | E21: =D21/$D$24*100 -> 10.208466 | F21: Smallcap | G21: =(9.03/1)*C21 -> 16479.75 | H21: Aug23 | I21: =(Stocks!E20*C21)/(G21*100000) -> 0.59516501 | J21: 1285 | L21: 2016 | M21: 11143.08 | N21: 12031.34 | O21: =(N21-M21)/M21 -> 0.079714047 | P21: =(N21-$M$17)/$M$17 -> 1.342984 | R21: 2016 | S21: 26117.54 | T21: 26626.46 | U21: =(T21-S21)/S21 -> 0.019485756 | V21: =(T21-$S$17)/$S$17 -> 0.72284683
A22: LIQUIDCASE | B22: 4381 | C22: =Stocks!C23 -> 115.82 | D22: =B22*C22 -> 507407.42 | E22: =D22/$D$24*100 -> 0.72220733 | L22: 2017 | M22: 12031.34 | N22: 17822.4 | O22: =(N22-M22)/M22 -> 0.48133126 | P22: =(N22-$M$17)/$M$17 -> 2.4707354 | R22: 2017 | S22: 26626.46 | T22: 34056.83 | U22: =(T22-S22)/S22 -> 0.27905963 | V22: =(T22-$S$17)/$S$17 -> 1.2036238
L23: 2018 | M23: 17822.4 | N23: 15438.45 | O23: =(N23-M23)/M23 -> -0.13376145 | P23: =(N23-$M$17)/$M$17 -> 2.0064848 | R23: 2018 | S23: 34056.83 | T23: 36068.33 | U23: =(T23-S23)/S23 -> 0.059063043 | V23: =(T23-$S$17)/$S$17 -> 1.3337766
A24: Total_Value | D24: =SUM(D3:D22) -> 70257860 | E24: =D24/$D$24*100 -> 100 | L24: 2019 | M24: 15438.45 | N24: 14967.83 | O24: =(N24-M24)/M24 -> -0.03048363 | P24: =(N24-$M$17)/$M$17 -> 1.9148363 | R24: 2019 | S24: 36068.33 | T24: 41253.74 | U24: =(T24-S24)/S24 -> 0.14376629 | V24: =(T24-$S$17)/$S$17 -> 1.669295
L25: 2020 | M25: 14967.83 | N25: 17941.43 | O25: =(N25-M25)/M25 -> 0.19866607 | P25: =(N25-$M$17)/$M$17 -> 2.4939153 | R25: 2020 | S25: 41253.74 | T25: 47751.33 | U25: =(T25-S25)/S25 -> 0.15750305 | V25: =(T25-$S$17)/$S$17 -> 2.0897171
L26: 2021 | M26: 17941.43 | N26: 24970.08 | O26: =(N26-M26)/M26 -> 0.39175528 | P26: =(N26-$M$17)/$M$17 -> 3.8626751 | R26: 2021 | S26: 47751.33 | T26: 58253.82 | U26: =(T26-S26)/S26 -> 0.21994131 | V26: =(T26-$S$17)/$S$17 -> 2.7692735
L27: 2022 | M27: 24970.08 | N27: 25314.5 | O27: =(N27-M27)/M27 -> 0.013793308 | P27: =(N27-$M$17)/$M$17 -> 3.9297475 | R27: 2022 | S27: 58253.82 | T27: 60840.74 | U27: =(T27-S27)/S27 -> 0.044407732 | V27: =(T27-$S$17)/$S$17 -> 2.9366584
L28: 2023 | M28: 25314.5 | N28: 36839.22 | O28: =(N28-M28)/M28 -> 0.45526161 | P28: =(N28-$M$17)/$M$17 -> 6.1740723 | R28: 2023 | S28: 60840.74 | T28: 72240.26 | U28: =(T28-S28)/S28 -> 0.18736656 | V28: =(T28-$S$17)/$S$17 -> 3.6742565
L29: 2024 | M29: 36839.22 | N29: 46444.66 | O29: =(N29-M29)/M29 -> 0.26073951 | P29: =(N29-$M$17)/$M$17 -> 8.0446364 | R29: 2024 | S29: 72240.26 | T29: 78139.01 | U29: =(T29-S29)/S29 -> 0.081654606 | V29: =(T29-$S$17)/$S$17 -> 4.0559311
L30: 2025 | M30: 46444.66 | N30: 46954.34 | O30: =(N30-M30)/M30 -> 0.01097392 | P30: =(N30-$M$17)/$M$17 -> 8.1438915 | R30: 2025 | S30: 78139.01 | T30: 85220.6 | U30: =(T30-S30)/S30 -> 0.0906281 | V30: =(T30-$S$17)/$S$17 -> 4.5141405
L31: 2026 | M31: 46954.34 | N31: =Stocks!C25 -> 49203.59 | O31: =(N31-M31)/M31 -> 0.04790292 | P31: =(N31-$M$17)/$M$17 -> 8.5819106 | R31: 2026 | S31: 85220.6 | T31: =Stocks!C24 -> 76957.27 | U31: =(T31-S31)/S31 -> -0.096963997 | V31: =(T31-$S$17)/$S$17 -> 3.9794674
K33: BSE500 | L33: 2012 | M33: 5778.68 | N33: 7581.57 | O33: =(N33-M33)/M33 -> 0.31198994
L34: 2013 | M34: 7581.57 | N34: 7828.34 | O34: =(N34-M34)/M34 -> 0.032548667 | P34: =(N34-$M$33)/$M$33 -> 0.35469346
L35: 2014 | M35: 7828.34 | N35: 10721.62 | O35: =(N35-M35)/M35 -> 0.36959049 | P35: =(N35-$M$33)/$M$33 -> 0.85537528
L36: 2015 | M36: 10721.62 | N36: 10634.22 | O36: =(N36-M36)/M36 -> -0.0081517532 | P36: =(N36-$M$33)/$M$33 -> 0.84025071
L37: 2016 | M37: 10634.22 | N37: 11036.44 | O37: =(N37-M37)/M37 -> 0.037823178 | P37: =(N37-$M$33)/$M$33 -> 0.90985485
L38: 2017 | M38: 11036.44 | N38: 15002.73 | O38: =(N38-M38)/M38 -> 0.35938129 | P38: =(N38-$M$33)/$M$33 -> 1.5962209
L39: 2018 | M39: 15002.73 | N39: 14540.39 | O39: =(N39-M39)/M39 -> -0.030817058 | P39: =(N39-$M$33)/$M$33 -> 1.516213
L40: 2019 | M40: 14540.39 | N40: 15667.44 | O40: =(N40-M40)/M40 -> 0.077511676 | P40: =(N40-$M$33)/$M$33 -> 1.7112489
L41: 2020 | M41: 15667.44 | N41: 18300.1 | O41: =(N41-M41)/M41 -> 0.16803383 | P41: =(N41-$M$33)/$M$33 -> 2.1668305
L42: 2021 | M42: 18300.1 | N42: 23811 | O42: =(N42-M42)/M42 -> 0.30114043 | P42: =(N42-$M$33)/$M$33 -> 3.1204912
L43: 2022 | M43: 23811 | N43: 24605.78 | O43: =(N43-M43)/M43 -> 0.033378691 | P43: =(N43-$M$33)/$M$33 -> 3.2580278
L44: 2023 | M44: 24605.78 | N44: 30720.28 | O44: =(N44-M44)/M44 -> 0.24849852 | P44: =(N44-$M$33)/$M$33 -> 4.3161414
L45: 2024 | M45: 30720.28 | N45: 35189.03 | O45: =(N45-M45)/M45 -> 0.1454658 | P45: =(N45-$M$33)/$M$33 -> 5.0894581
L46: 2025 | M46: 35189.03 | N46: 37443.41 | O46: =(N46-M46)/M46 -> 0.064064852 | P46: =(N46-$M$33)/$M$33 -> 5.4795784
L47: 2026 | M47: 37443.41 | N47: =Stocks!C27 -> 36615.95 | O47: =(N47-M47)/M47 -> -0.022098949 | P47: =(N47-$M$33)/$M$33 -> 5.3363865
